Workbook
Name UPDATE: 'Data Sheet'!$E$1

Sheet Assumptions
C1: Bharat Electronics Ltd
B5: Company Name | C5: BHARAT ELECTRONICS LTD
B6: ISIN Code | C6: INE263A01024
B7: Sector Name | C7: AEROSPACE & DEFENCE
B8: Industry | C8: ELECTRONICS & DEFENCE
B9: Exchange Name | C9: BSE: 532959, NSE: BEL
B10: Website | C10: https://bel-india.in | AN10: Particulars | AO10: FY2026 | AP10: FY2027 | AQ10: FY2028 | AR10: FY2029 | AS10: FY2030 | AT10: FY2031 | AU10: FY2032 | AV10: FY2033 | AW10: FY2034 | AX10: FY2035
B11: Company Description | C11: Bharat Electronics Ltd (BEL) is a government-owned aerospace and defence electronics company under the Ministry of Defence, Government of India. The company designs, develops, manufactures, and supplies advanced electronic systems and equipment for defence and civilian applications. Its product portfolio includes radar systems, sonar systems, electronic warfare systems, communication systems, weapon systems, avionics, night vision devices, electro-optics, and homeland security solutions. BEL also provides software-defined radios, satellite communication systems, electronic voting machines, and smart city solutions. It primarily serves the Indian Army, Indian Navy, Indian Air Force, Indian Coast Guard, DRDO, ISRO, and Paramilitary forces, along with select export markets. BEL is headquartered in Bengaluru, Karnataka, India. | AN11: Base Case | AO11: 0.15 | AP11: 0.14 | AQ11: 0.135 | AR11: 0.13 | AS11: 0.125 | AT11: 0.12 | AU11: 0.115 | AV11: 0.11 | AW11: 0.105 | AX11: 0.1
B12: Price (INR) | C12: 272 | AN12: Bull Case | AO12: 0.18 | AP12: 0.17 | AQ12: 0.17 | AR12: 0.16 | AS12: 0.15 | AT12: 0.145 | AU12: 0.14 | AV12: 0.135 | AW12: 0.13 | AX12: 0.125
AN13: Bear Case | AO13: 0.1 | AP13: 0.095 | AQ13: 0.09 | AR13: 0.085 | AS13: 0.08 | AT13: 0.075 | AU13: 0.07 | AV13: 0.065 | AW13: 0.06 | AX13: 0.055
B14: Assumption Type | C14: Case No.
B15: Bull Case | C15: 2
D18: Particulars | E18: FY2026 | F18: FY2027 | G18: FY2028 | H18: FY2029 | I18: FY2030 | J18: FY2031 | K18: FY2032 | L18: FY2033 | M18: FY2034 | N18: FY2035
B19: Transaction Date | C19: 45516 | D19: Base Case | E19: 0.15 | F19: 0.14 | G19: 0.135 | H19: 0.13 | I19: 0.125 | J19: 0.12 | K19: 0.115 | L19: 0.11 | M19: 0.105 | N19: 0.1
B20: Fiscal Year End | C20: 45747 | D20: Bull Case | E20: 0.18 | F20: 0.17 | G20: 0.17 | H20: 0.16 | I20: 0.15 | J20: 0.145 | K20: 0.14 | L20: 0.135 | M20: 0.13 | N20: 0.125
B21: Risk Free Rate | C21: 0.07192 | D21: Bear Case | E21: 0.1 | F21: 0.095 | G21: 0.09 | H21: 0.085 | I21: 0.08 | J21: 0.075 | K21: 0.07 | L21: 0.065 | M21: 0.06 | N21: 0.055
B22: Tax Rate | C22: 0.255
B23: EV/EBITDA Multiple | C23: ='[1]comps valuation'!R11 -> 5.4069884
B24: Perpetual Growth Rate | C24: 0.06
B25: Discount Rate | C25: =WACC!G36 -> 0.255
B26: Shares Outstanding | C26: ='[1]comps valuation'!G11 -> 2029.4
B27: Current Price | C27: 272
B28: Sheet Name | C28: Row/Cell Referencing | D28: Comments
B29: Assumptions | C29: Case Selection Cell | D29: User selection dropdown provided with three scenarios — Base, Bull, Bear. Model assumptions and projections will dynamically update based on selected case.
B30: Assumptions | C30: Revenue Growth Input Cells | D30: User input cells provided for revenue growth rates per year. Historical 5-year revenue CAGR of ~13.8% (FY2021–FY2025) has been used as the base driver for forecasting future revenues.
B31: Assumptions | C31: Risk Free Rate Cell | D31: 10-year India Government benchmark bond yield linked across the model wherever required for WACC and DCF calculations.
B32: Assumptions | C32: General | D32: Past 5 years revenue growth trend (FY2021–FY2025) used as primary driver to forecast revenue. Other income forecasted using 5-year historical average as a percentage of revenue.
B33: Assumptions | C33: Perpetual Growth Rate | D33: A mild tapering rate of 6% has been assumed considering stable defence budget allocations, strong order book visibility, and Government of India's Atmanirbhar Bharat push for domestic defence production.
B34: Forecasts & Supporting Schedules | C34: Receivable / Payable / Inventory Days | D34: Past 4-year average trend used to forecast working capital days. FY2021 has been excluded from the average due to COVID-19 distortion in receivable and inventory days relative to the normal operating cycle.
B35: Forecasts & Supporting Schedules | C35: Cost Drivers | D35: Historical 5-year average growth rates used to forecast future costs. For COGS and salaries, past 3-year trend preferred to reduce pandemic-period distortion in FY2021–FY2022.
B36: Forecasts & Supporting Schedules | C36: Depreciation & Interest | D36: Depreciation taken as % of opening gross PP&E. Interest taken as % of revenue. Depreciation rate assumed to increase by ~1% every 2 years reflecting BEL's ongoing capacity expansion across its nine manufacturing units.
B37: Forecasts & Supporting Schedules | C37: Capex | D37: BEL's historical capex growth ranges from 15–25% YoY driven by modernisation of manufacturing facilities and new product development. Capex assumed to grow at minimum 8% per year on a conservative basis, consistent with India's defence indigenisation roadmap and BEL's expanding order book.
B38: Forecasts & Supporting Schedules | C38: Dividend Payout | D38: FY2021 excluded from average payout ratio calculation due to COVID-19-related atypical dividend behaviour. BEL has maintained a consistent payout ratio of ~34–36% in FY2022–FY2025, which has been used as the forecast base.
B39: Forecasts & Supporting Schedules | C39: Tax Rate | D39: Effective tax rate assumed to remain stable at ~25.2% with a marginal increase of 0.5% every two years in line with potential changes in corporate tax policy.
B40: Ratio Analysis | C40: General | D40: Ratio interpretations designed for presentation clarity. Key ratios include ROCE, ROE, Asset Turnover, Current Ratio, Debt-to-Equity, and Order Book-to-Revenue coverage ratio, with expandable commentary for each.

Sheet Historial IS
E1: Bharat Electronics Ltd
B2: Historical Financial Information
A3: # | B3: INCOME STATEMENT | K3: ='Data Sheet'!G16 -> 44286 | L3: ='Data Sheet'!H16 -> 44651 | M3: ='Data Sheet'!I16 -> 45016 | N3: ='Data Sheet'!J16 -> 45382 | O3: ='Data Sheet'!K16 -> 45747
B4: Revenue from Operations | K4: 1406383 | L4: 1531376 | M4: 1764620 | N4: 2016939 | O4: 2365801
B5: Other Income | K5: 12610 | L5: 23359 | M5: 36002 | N5: 75584 | O5: 76759
B6: Total Income ( I + II ) | K6: =SUM(K4:K5) -> 1418993 | L6: =SUM(L4:L5) -> 1554735 | M6: =SUM(M4:M5) -> 1800622 | N6: =SUM(N4:N5) -> 2092523 | O6: =SUM(O4:O5) -> 2442560
B8: EXPENSES
B9: Cost of Materials Consumed | K9: -668520 | L9: -809634 | M9: -937844 | N9: -1049762 | O9: -1256140
B10: Purchases of Stock - in - Trade | K10: -123321 | L10: -105349 | M10: -82785 | N10: -62886 | O10: -43041
B11: Changes in Inventories of Finished Goods , Stock - in - Trade , Work - in - Progress and Scrap | K11: -12933 | L11: -27697 | M11: -39745 | N11: -56057 | O11: -81083
B12: Employee Benefits Expense | K12: -194068 | L12: -210939 | M12: -229773 | N12: -246670 | O12: -273436
B13: Finance Costs | K13: -608 | L13: -485 | M13: -1479 | N13: -702 | O13: -961
B14: Depreciation and Amortization Expense | K14: -36633 | L14: -38018 | M14: -40787 | N14: -41243 | O14: -43558
B15: Other Expenses | K15: -111421 | L15: -99263 | M15: -149211 | N15: -213861 | O15: -197508 | T15: =T11+T12 -> 0
B16: Total Gross Expenses | K16: =SUM(K9:K15) -> -1147504 | L16: =SUM(L9:L15) -> -1291385 | M16: =SUM(M9:M15) -> -1481624 | N16: =SUM(N9:N15) -> -1671181 | O16: =SUM(O9:O15) -> -1895727
B17: Less : Expenses relating to Capital and Other Accounts | K17: 0 | L17: 0 | M17: 0 | N17: 0 | O17: 0
B18: Total expenses ( IV ) | K18: =K16 -> -1147504 | L18: =L16 -> -1291385 | M18: =M16 -> -1481624 | N18: =N16 -> -1671181 | O18: =O16 -> -1895727
B20: Profit / ( loss ) before tax | K20: =K6-K18 -> 2566497 | L20: =L6-L18 -> 2846120 | M20: =M6-M18 -> 3282246 | N20: =N6-N18 -> 3763704 | O20: =O6-O18 -> 4338287
B22: Tax expense :
B23: ( 1 ) Current Tax | K23: -82493 | L23: -91052 | M23: -87446 | N23: -144959 | O23: -176135
B24: ( 2 ) Earlier Year Tax Refund / Liability | K24: -2492 | L24: 0 | M24: -2001 | N24: -6890 | O24: 274
B25: ( 3 ) Deferred Tax | K25: 6938 | L25: -10165 | M25: 12376 | N25: -6613 | O25: 3765
B26: Total tax exp | K26: =SUM(K23:K25) -> -78047 | L26: =SUM(L23:L25) -> -101217 | M26: =SUM(M23:M25) -> -77071 | N26: =SUM(N23:N25) -> -158462 | O26: =SUM(O23:O25) -> -172096
B28: Profit ( Loss ) for the period from Continuing Operations ( IX - X ) | K28: =K20-K26 -> 2644544 | L28: =L20-L26 -> 2947337 | M28: =M20-M26 -> 3359317 | N28: =N20-N26 -> 3922166 | O28: =O20-O26 -> 4510383
B29: Profit / ( loss ) from Discontinued Operations | K29: 0 | L29: 0 | M29: 0 | N29: 0 | O29: 0
B30: Tax expense of Discontinued Operations | K30: 0 | L30: 0 | M30: 0 | N30: 0 | O30: 0
B31: Profit / ( loss ) from Discontinued Operations ( after tax ) ( XII - XIII ) | K31: 0 | L31: 0 | M31: 0 | N31: 0 | O31: 0
B32: Profit / ( loss ) for the period ( XI + XIV ) | K32: =SUM(K28:K31) -> 2644544 | L32: =SUM(L28:L31) -> 2947337 | M32: =SUM(M28:M31) -> 3359317 | N32: =SUM(N28:N31) -> 3922166 | O32: =SUM(O28:O31) -> 4510383
B34: KPIs | K34: =K3 -> 44286 | L34: =L3 -> 44651 | M34: =M3 -> 45016 | N34: =N3 -> 45382 | O34: =O3 -> 45747
B35: Revenue % (y-o-y) | K35: 0 | L35: =(L4/K4)-1 -> 0.088875505 | M35: =(M4/L4)-1 -> 0.15231008 | N35: =(N4/M4)-1 -> 0.14298773 | O35: =(O4/N4)-1 -> 0.17296606
B36: GP% | K36: ='Ratio analysis'!C15 -> 0.42777039 | L36: ='Ratio analysis'!D15 -> 0.3844229 | M36: ='Ratio analysis'!E15 -> 0.39909216 | N36: ='Ratio analysis'!F15 -> 0.42055511 | O36: ='Ratio analysis'!G15 -> 0.41657646
B37: EBITDA% | K37: ='Forecasts & support schedules'!D33/'Forecasts & support schedules'!D27 -> 0.21055431 | L37: ='Forecasts & support schedules'!E33/'Forecasts & support schedules'!E27 -> 0.18185867 | M37: ='Forecasts & support schedules'!F33/'Forecasts & support schedules'!F27 -> 0.1843241 | N37: ='Forecasts & support schedules'!G33/'Forecasts & support schedules'!G27 -> 0.19222346 | O37: ='Forecasts & support schedules'!H33/'Forecasts & support schedules'!H27 -> 0.21751322
B38: EBIT % | K38: ='Forecasts & support schedules'!D35/'Forecasts & support schedules'!D27 -> 0.18450664 | L38: ='Forecasts & support schedules'!E35/'Forecasts & support schedules'!E27 -> 0.15703263 | M38: ='Forecasts & support schedules'!F35/'Forecasts & support schedules'!F27 -> 0.16121035 | N38: ='Forecasts & support schedules'!G35/'Forecasts & support schedules'!G27 -> 0.17177515 | O38: ='Forecasts & support schedules'!H35/'Forecasts & support schedules'!H27 -> 0.1991017
B39: NP % | K39: ='Forecasts & support schedules'!D44/'Forecasts & support schedules'!D27 -> 0.13754575 | L39: ='Forecasts & support schedules'!E44/'Forecasts & support schedules'!E27 -> 0.10587406 | M39: ='Forecasts & support schedules'!F44/'Forecasts & support schedules'!F27 -> 0.13709864 | N39: ='Forecasts & support schedules'!G44/'Forecasts & support schedules'!G27 -> 0.13033612 | O39: ='Forecasts & support schedules'!H44/'Forecasts & support schedules'!H27 -> 0.15839752
B40: Asset Turnover | K40: ='Ratio analysis'!C25 -> 0.44365219 | L40: ='Ratio analysis'!D25 -> 0.44130245 | M40: ='Ratio analysis'!E25 -> 0.47044319 | N40: ='Ratio analysis'!F25 -> 0.50197991 | O40: ='Ratio analysis'!G25 -> 0.57940074

Sheet Historical BS
E1: Bharat Electronics Ltd
B2: Historical Financial Information
A3: # | B3: BALANCE SHEET | K3: ='Data Sheet'!G16 -> 44286 | L3: ='Data Sheet'!H16 -> 44651 | M3: ='Data Sheet'!I16 -> 45016 | N3: ='Data Sheet'!J16 -> 45382 | O3: ='Data Sheet'!K16 -> 45747
A4: v
B5: ASSETS
B6: Non - current assets
B7: ( a ) Property , Plant and Equipment | K7: 248550 | L7: 250937 | M7: 269431 | N7: 278847 | O7: 320453
B8: ( b ) Capital work - in - progress | K8: 39747 | L8: 44593 | M8: 36123 | N8: 45642 | O8: 47698
B9: ( c ) Investment Property | K9: 8 | L9: 7 | M9: 6 | N9: 4 | O9: 4
B10: ( d ) Goodwill | K10: 0 | L10: 0 | M10: 0 | N10: 0 | O10: 0
B11: ( e ) Other Intangible assets | K11: 16656 | L11: 16582 | M11: 26849 | N11: 24670 | O11: 21466
B12: ( f ) Intangible Assets under Development | K12: 48521 | L12: 56011 | M12: 49371 | N12: 43730 | O12: 57482
B13: ( g ) Investments accounted for using the Equity Method | K13: 18989 | L13: 23292 | M13: 20073 | N13: 15157 | O13: 16136
B14: ( h ) Financial Assets
B15: ( i ) Investments | K15: 111605 | L15: 133910 | M15: 44926 | N15: 53066 | O15: 58161
B16: ( ii ) Trade Receivables | K16: 0 | L16: 0 | M16: 0 | N16: 0 | O16: 0
B17: ( iii ) Contract Assets | K17: 0 | L17: 0 | M17: 0 | N17: 0 | O17: 0
B18: ( iv ) Loans | K18: 736 | L18: 728 | M18: 656 | N18: 703 | O18: 663
B19: ( v ) Other Financial Assets | K19: 2871 | L19: 2417 | M19: 2045 | N19: 1883 | O19: 2415
B20: ( i ) Deferred tax Assets ( Net ) | K20: 46346 | L20: 62094 | M20: 50372 | N20: 57468 | O20: 53484
B21: ( j ) Inventories | K21: 3938 | L21: 2734 | M21: 587 | N21: 0 | O21: 0
B22: ( k ) Other Non - Current Assets | K22: 39669 | L22: 68382 | M22: 43904 | N22: 25200 | O22: 19436
B23: Total non - current assets | K23: =SUM(K7:K22) -> 577636 | L23: =SUM(L7:L22) -> 661687 | M23: =SUM(M7:M22) -> 544343 | N23: =SUM(N7:N22) -> 546370 | O23: =SUM(O7:O22) -> 597398
B25: Current assets
B26: ( a ) Inventories | K26: 496798 | L26: 559190 | M26: 644804 | N26: 744689 | O26: 911898
B27: ( b ) Financial Assets
B28: ( i ) Investments
B29: ( ii ) Trade receivables | K29: 656199 | L29: 610809 | M29: 703348 | N29: 739238 | O29: 911637
B30: ( iii ) Contract Assets
B31: ( iv ) Cash and Cash Equivalents | K31: 304290 | L31: 130086 | M31: 394569 | N31: 120632 | O31: 71345
B32: Bank Balances other than Cash and Cash Equivalents | K32: 203086 | L32: 626288 | M32: 416589 | N32: 985027 | O32: 883165
B33: ( vi ) Loans | K33: 152 | L33: 148 | M33: 172 | N33: 141 | O33: 147
B34: ( vii ) Other Financial Assets | K34: 6066 | L34: 10254 | M34: 20342 | N34: 29440 | O34: 24133
B35: ( c ) Current Tax Assets ( Net ) | K35: 13364 | L35: 14474 | M35: 40314 | N35: 44961 | O35: 35362
B36: ( d ) Other Currents Assets | K36: 691376 | L36: 778122 | M36: 784636 | N36: 742170 | O36: 648101
B37: Total current assets | K37: =SUM(K26:K36) -> 2371331 | L37: =SUM(L26:L36) -> 2729371 | M37: =SUM(M26:M36) -> 3004774 | N37: =SUM(N26:N36) -> 3406298 | O37: =SUM(O26:O36) -> 3485788
B39: Assets held for Sale | K39: 0 | L39: 0 | M39: 81.1 | N39: 81.1 | O39: 0
B40: Total Assets | K40: =SUM(K23,K37,K39) -> 2948967 | L40: =SUM(L23,L37,L39) -> 3391058 | M40: =SUM(M23,M37,M39) -> 3549198.1 | N40: =SUM(N23,N37,N39) -> 3952749.1 | O40: =SUM(O23,O37,O39) -> 4083186
B42: EQUITY AND LIABILITIES
B43: Equity
B44: ( a ) Equity Share capital | K44: 24366 | L44: 24366 | M44: 73098 | N44: 73098 | O44: 73098
B45: ( b ) Other Equity | K45: 1081592 | L45: 1204227 | M45: 1313065 | N45: 1559549 | O45: 1924291
B46: Equity attributable to owners of the parent | K46: =SUM(K44:K45) -> 1105958 | L46: =SUM(L44:L45) -> 1228593 | M46: =SUM(M44:M45) -> 1386163 | N46: =SUM(N44:N45) -> 1632647 | O46: =SUM(O44:O45) -> 1997389
B47: Non - controlling interest | K47: 1499 | L47: 1634 | M47: 1775 | N47: 1792 | O47: 1894
B48: Total equity | K48: =SUM(K46:K47) -> 1107457 | L48: =SUM(L46:L47) -> 1230227 | M48: =SUM(M46:M47) -> 1387938 | N48: =SUM(N46:N47) -> 1634439 | O48: =SUM(O46:O47) -> 1999283
B50: LIABILITIES
B51: Non - current liabilities
B52: ( a ) Financial Liabilities
B53: ( i ) Borrowings
B54: ( ia ) Lease Liabilities | K54: 117 | L54: 5151 | M54: 5942 | N54: 6025 | O54: 5869
B55: ( ii ) Trade payables
B56: A ) total outstanding dues of micro enterprises and small enterprises
B57: B ) total outstanding dues of creditors other than micro enterprises and small enterprises | K57: 29 | L57: 34 | M57: 37 | N57: 0 | O57: 0
B58: Sub Total - Trade payables | K58: 0 | L58: 0 | M58: 0 | N58: 0 | O58: 0
B59: ( iii ) Other Financial Liabilities | K59: 671 | L59: 2022 | M59: 473 | N59: 480 | O59: 1457
B60: ( b ) Provisions | K60: 141203 | L60: 180532 | M60: 84465 | N60: 96728 | O60: 90216
B61: ( c ) Deferred Tax Liabilities ( Net ) | K61: 36 | L61: 145 | M61: 289 | N61: 547 | O61: 952
B62: ( d ) Other Non - Current Liabilities | K62: 16499 | L62: 14843 | M62: 13395 | N62: 11776 | O62: 10155
B63: Total non - current liabilities | K63: =SUM(K53:K62) -> 158555 | L63: =SUM(L53:L62) -> 202727 | M63: =SUM(M53:M62) -> 104601 | N63: =SUM(N53:N62) -> 115556 | O63: =SUM(O53:O62) -> 108649
B65: Current Liabilities
B66: ( a ) Financial liabilities
B67: ( i ) Borrowings
B68: ( ia ) Lease Liabilities | K68: 135 | L68: 119 | M68: 192 | N68: 226 | O68: 254
B69: ( ii ) Trade payables
B70: A ) total outstanding dues of micro enterprises and small enterprises | K70: 15343 | L70: 24844 | M70: 20754 | N70: 21306 | O70: 17777
B71: B ) total outstanding dues of creditors other than micro enterprises and small enterprises | K71: 314547 | L71: 312086 | M71: 312284 | N71: 349325 | O71: 316100
B72: Sub Total - Trade payables | K72: =K70+K71 -> 329890 | L72: =L70+L71 -> 336930 | M72: =M70+M71 -> 333038 | N72: =N70+N71 -> 370631 | O72: =O70+O71 -> 333877
B73: ( iii ) Other Financial liabilities | K73: 95895 | L73: 96043 | M73: 129023 | N73: 131714 | O73: 136832
B74: ( b ) Other Current Liabilities | K74: 1220296 | L74: 1480907 | M74: 1529906 | N74: 1628984 | O74: 1428702
B75: ( c ) Provisions | K75: 35028 | L75: 42382 | M75: 62754 | N75: 69453 | O75: 73971
B76: ( d ) Current tax liabilities ( Net ) | K76: 0 | L76: 69 | M76: 0 | N76: 28 | O76: 0
B77: ( e ) Deferred Income | K77: 1711 | L77: 1654 | M77: 1665 | N77: 1637 | O77: 1618
B78: Total current liabilities | K78: =SUM(K67:K68,K72:K77) -> 1682955 | L78: =SUM(L67:L68,L72:L77) -> 1958104 | M78: =SUM(M67:M68,M72:M77) -> 2056578 | N78: =SUM(N67:N68,N72:N77) -> 2202673 | O78: =SUM(O67:O68,O72:O77) -> 1975254
B80: Total Equity and Liabilities | K80: =SUM(K48,K63,K78) -> 2948967 | L80: =SUM(L48,L63,L78) -> 3391058 | M80: =SUM(M48,M63,M78) -> 3549117 | N80: =SUM(N48,N63,N78) -> 3952668 | O80: =SUM(O48,O63,O78) -> 4083186
B83: KPIs
B84: Liquidity ratios
B85: Quick ratio | K85: ='Ratio analysis'!C6 -> 0.6356575 | L85: ='Ratio analysis'!D6 -> 0.63997165 | M85: ='Ratio analysis'!E6 -> 0.66494568 | N85: ='Ratio analysis'!F6 -> 0.67337024 | O85: ='Ratio analysis'!G6 -> 0.63036315
B86: Current ratio | K86: ='Ratio analysis'!C7 -> 0.8041226 | L86: ='Ratio analysis'!D7 -> 0.80487299 | M86: ='Ratio analysis'!E7 -> 0.84662579 | N86: ='Ratio analysis'!F7 -> 0.86177185 | O86: ='Ratio analysis'!G7 -> 0.85369317

Sheet Historical CF
B1: Bharat Electronics Ltd
B2: Historical Financial Information
A3: # | B3: CASH FLOW STATEMENT | F3: ='Historical BS'!K3 -> 44286 | G3: ='Historical BS'!L3 -> 44651 | H3: ='Historical BS'!M3 -> 45016 | I3: ='Historical BS'!N3 -> 45382 | J3: ='Historical BS'!O3 -> 45747
B5: Cash flow from Operating Activities
B6: Profit after share of associate (before exceptional items & tax) | F6: 297220 | G6: 321200 | H6: 396880 | I6: 530834 | J6: 713453
B7: Adjustments for:
B8: Depreciation and amortisation expense | F8: 38732 | G8: 40113 | H8: 42882 | I8: 44320 | J8: 46738
B9: Provision for intangible assets under development | F9: 7213 | G9: 0 | H9: 544 | I9: 9666 | J9: 0
B10: Intangible assets under development charged off | F10: 75 | G10: 0 | H10: 1950 | I10: 0 | J10: 129
B11: Capital WIP charged off | F11: 1468 | G11: 0 | H11: 0 | I11: 0 | J11: 0
B12: Provision Others – Contract costs | F12: 0 | G12: 0 | H12: 4180 | I12: 2 | J12: 0
B13: Prov. for doubtful debts, liq. damages & disallowances (net) | F13: 0 | G13: 0 | H13: 37536 | I13: 83118 | J13: 0
B14: Provision for doubtful advances, claims (net of withdrawal) | F14: 0 | G14: 0 | H14: 0 | I14: 1913 | J14: 0
B15: Provision for performance warranty (net) | F15: 0 | G15: 0 | H15: 0 | I15: 16852 | J15: 0
B16: Provision for onerous contract (net) | F16: 0 | G16: 0 | H16: 0 | I16: 3132 | J16: 0
B17: Provision for obsolete/redundant materials (net) | F17: 0 | G17: 0 | H17: 0 | I17: 7235 | J17: 0
B18: Corporate social responsibility | F18: 4711 | G18: 5348 | H18: 5770 | I18: 0 | J18: 0
B19: Transfer from government grants | F19: -1736 | G19: -1713 | H19: -1665 | I19: -1657 | J19: -1647
... B23: Profit on sale of property, plant & equipment | F23: -121 | G23: -45 | H23: -152 | I23: -702 | J23: -255
B24: Operating Profit Before Working Capital Changes | F24: =SUM(F6:F23) -> 342149 | G24: =SUM(G6:G23) -> 347763 | H24: =SUM(H6:H23) -> 463332 | I24: =SUM(I6:I23) -> 638232 | J24: =SUM(J6:J23) -> 697152
B26: Adjustments for :
B27: Increase / (Decrease) due to
B28: Trade receivables | F28: 16203 | G28: 45390 | H28: -92539 | I28: -119008 | J28: -172399
B29: Loans | F29: 4079 | G29: 12 | H29: 48 | I29: -16 | J29: 34
B30: Other financial assets | F30: -2713 | G30: -3456 | H30: -9456 | I30: 4565 | J30: 278
B31: Other assets | F31: -90272 | G31: -115459 | H31: 13784 | I31: 59255 | J31: 99836
B32: Inventories | F32: -99651 | G32: -61188 | H32: -83467 | I32: -106533 | J32: -167209
B33: Trade payables | F33: 84886 | G33: 7045 | H33: -3889 | I33: 37556 | J33: -36754
B34: Other financial liabilities | F34: 7891 | G34: 6093 | H34: 32025 | I34: 3351 | J34: 6496
B35: Provisions | F35: 14650 | G35: 26755 | H35: -97882 | I35: -8694 | J35: -1026
B36: Other liabilities | F36: 297706 | G36: 260611 | H36: 48999 | I36: 99078 | J36: -200282
B37: Current tax assets | F37: -12299 | G37: -12415 | H37: -15411 | I37: 0 | J37: 0
B38: Cash Generated from Operations | F38: =SUM(F24,F28:F37) -> 562629 | G38: =SUM(G24,G28:G37) -> 501151 | H38: =SUM(H24,H28:H37) -> 255544 | I38: =SUM(I24,I28:I37) -> 607786 | J38: =SUM(J24,J28:J37) -> 226126
B39: Income taxes paid (net) | F39: -53307 | G39: -80429 | H39: -91322 | I39: -141837 | J39: -167464
B40: Cash Flow Before Exceptional Items | F40: =SUM(F38:F39) -> 509322 | G40: =SUM(G38:G39) -> 420722 | H40: =SUM(H38:H39) -> 164222 | I40: =SUM(I38:I39) -> 465949 | J40: =SUM(J38:J39) -> 58662
B41: Exceptional items | F41: 0 | G41: 0 | H41: 0 | I41: 0 | J41: 0
B42: Net Cash ( used in ) / generated from Operating Activities ( A ) | F42: =F40+F41 -> 509322 | G42: =G40+G41 -> 420722 | H42: =H40+H41 -> 164222 | I42: =I40+I41 -> 465949 | J42: =J40+J41 -> 58662
B44: Cash flow from Investing Activities
B45: Purchase of PPE and other intangible assets | F45: -46925 | G45: -55456 | H45: -59045 | I45: -65253 | J45: -101128
B46: Receipt / Less: Receipt of grant | F46: 0 | G46: 0 | H46: 228 | I46: 10 | J46: 7
B47: Proceeds from sale of PPE | F47: 133 | G47: 740 | H47: 170 | I47: 853 | J47: 305
B48: Increase/(Decrease) in term deposits & other bank balances | F48: -199223 | G48: -423480 | H48: 209439 | I48: -569004 | J48: 101249
B49: Other investments | F49: -19557 | G49: -26615 | H49: 92204 | I49: -3251 | J49: -6083
B50: Interest received | F50: 6050 | G50: 17645 | H50: 26088 | I50: 44260 | J50: 67344
B51: Net Cash from / (used in) Investing Activities (B) | F51: =SUM(F45:F50) -> -259522 | G51: =SUM(G45:G50) -> -487166 | H51: =SUM(H45:H50) -> 269084 | I51: =SUM(I45:I50) -> -592385 | J51: =SUM(J45:J50) -> 61694
B53: Cash flow from Financing Activities
B54: Proceeds/Repayment from borrowings (net) | F54: -832 | G54: 0 | H54: 0 | I54: 0 | J54: 0
B55: Corporate Social Responsibility (CSR) expenditure | F55: -3670 | G55: -4757 | H55: 0 | I55: 0 | J55: 0
B56: Dividend paid (including tax on dividend) | F56: -102274 | G56: -102331 | H56: -124280 | I56: -146209 | J56: -168078
B57: Repayment of lease liabilities | F57: -159 | G57: -167 | H57: -433 | I57: -578 | J57: -597
B58: Interest on lease liability | F58: -24 | G58: -306 | H58: -370 | I58: -421 | J58: -416
B59: Finance costs | F59: -613 | G59: -199 | H59: -1125 | I59: -293 | J59: -552
B60: Net Cash ( used in ) / generated from Financing Activities ( C ) | F60: =SUM(F54:F59) -> -107572 | G60: =SUM(G54:G59) -> -107760 | H60: =SUM(H54:H59) -> -126208 | I60: =SUM(I54:I59) -> -147501 | J60: =SUM(J54:J59) -> -169643
B62: Net increase / ( decrease ) in Cash and Cash Equivalents ( A + B + C ) | F62: =SUM(F42,F51,F60) -> 142228 | G62: =SUM(G42,G51,G60) -> -174204 | H62: =SUM(H42,H51,H60) -> 307098 | I62: =SUM(I42,I51,I60) -> -273937 | J62: =SUM(J42,J51,J60) -> -49287
B63: Add : Cash and Cash Equivalents at the beginning of the year | F63: 162063 | G63: 304290 | H63: 130086 | I63: 394569 | J63: 120632
B64: Cash and Cash Equivalents at the end of the year | F64: =F62+F63 -> 304291 | G64: =G62+G63 -> 130086 | H64: =H62+H63 -> 437184 | I64: =I62+I63 -> 120632 | J64: =J62+J63 -> 71345

Sheet Summary
B1: Bharat Electronics Ltd
B3: Football Field Data
D5: Comps | E5: DCF | F5: 52-week hi/lo | G5: market consensus
B7: High | D7: =MAX('Comps valution'!I21:I23) -> 4585.6398 | E7: 219 | F7: 473 | G7: 593
B8: High | D8: =D7 -> 4585.6398 | E8: 219 | F8: =F7 -> 473 | G8: =G7 -> 593
B9: Low | D9: =MIN('Comps valution'!I21:I23) -> 128.47453 | E9: 65 | F9: 253 | G9: 263
B10: Low | D10: =D9 -> 128.47453 | E10: 65 | F10: =F9 -> 253 | G10: =G9 -> 263
B12: Valuation Summary

Sheet Beta
D1: Bharat Electronics Ltd
B2: Regression beta
C4: Index | D4: % Change | E4: Stock | F4: % Change
B5: Date | C5: Close Price | D5: Monthly | E5: Close Price | F5: Monthly
B6: 44317 | C6: 1505526495 | E6: 45.37
B7: 44348 | C7: 1186761072 | D7: =C7/C6-1 -> -0.2117302 | E7: 55.55 | F7: =E7/E6-1 -> 0.22437734
B8: 44378 | C8: 588864033 | D8: =C8/C7-1 -> -0.50380574 | E8: 57.62 | F8: =E8/E7-1 -> 0.037263726
B9: 44409 | C9: 573740100 | D9: =C9/C8-1 -> -0.025683234 | E9: 58.25 | F9: =E9/E8-1 -> 0.010933704
B10: 44440 | C10: 472297200 | D10: =C10/C9-1 -> -0.17680985 | E10: 63.33 | F10: =E10/E9-1 -> 0.0872103
B11: 44470 | C11: 399386091 | D11: =C11/C10-1 -> -0.15437548 | E11: 64.95 | F11: =E11/E10-1 -> 0.025580294
B12: 44501 | C12: 409649820 | D12: =C12/C11-1 -> 0.025698764 | E12: 63.97 | F12: =E12/E11-1 -> -0.01508853
B13: 44531 | C13: 367604007 | D13: =C13/C12-1 -> -0.10263843 | E13: 65.92 | F13: =E13/E12-1 -> 0.030483039
B14: 44562 | C14: 408048816 | D14: =C14/C13-1 -> 0.11002276 | E14: 65.84 | F14: =E14/E13-1 -> -0.0012135922
B15: 44593 | C15: 382511754 | D15: =C15/C14-1 -> -0.06258335 | E15: 66.08 | F15: =E15/E14-1 -> 0.0036452005
B16: 44621 | C16: 592569945 | D16: =C16/C15-1 -> 0.54915487 | E16: 66.69 | F16: =E16/E15-1 -> 0.0092312349
B17: 44652 | C17: 756720162 | D17: =C17/C16-1 -> 0.27701408 | E17: 76.02 | F17: =E17/E16-1 -> 0.13990103
B18: 44682 | C18: 344665149 | D18: =C18/C17-1 -> -0.5445276 | E18: 74.81 | F18: =E18/E17-1 -> -0.015916864
... B52: 45717 | C52: 434656933 | D52: =C52/C51-1 -> -0.083965369 | E52: 297.7 | F52: =E52/E51-1 -> 0.22364257

Sheet Market Data
D1: Bharat Electronics Ltd
B2: Equity Market Return
C4: Index
B5: Date | C5: Close Price
B6: 42072 | C6: 8756.75 | E6: Yearfrac | F6: =YEARFRAC(B6,B2714) -> 10.991667
B7: 42073 | C7: 8712.05
B8: 42074 | C8: 8699.95 | E8: Market Return | F8: =_xlfn.RRI(F6,C6,C2714) -> 0.097920997
B9: 42075 | C9: 8776
B10: 42076 | C10: 8647.75
B11: 42079 | C11: 8633.15
B12: 42080 | C12: 8723.3
B13: 42081 | C13: 8685.9
B14: 42082 | C14: 8634.65
B15: 42083 | C15: 8570.9
B16: 42086 | C16: 8550.9
B17: 42087 | C17: 8542.95
B18: 42088 | C18: 8530.8
B19: 42089 | C19: 8342.15
B20: 42090 | C20: 8341.4
... B2714: 46087 | C2714: 24450.45

Sheet Comps valution
B1: Bharat Electronics Ltd
B3: Comps Valuation
E5: Market Data | L5: Financial Data | P5: Valuation
E6: Price | F6: Shares | G6: Market Cap | H6: Debt | I6: Cash | J6: EV | L6: Sales | M6: EBITDA | N6: Earnings | P6: EV/Sales | Q6: EV/EBITDA | R6: P/E
B7: Company Name | C7: Ticker | E7: (₹/share) | F7: number | G7: ₹ MM | I7: & Equivalents | J7: ₹ MM | L7: ₹ MM | M7: ₹ MM | N7: ₹ MM | P7: x | Q7: x | R7: x
B8: Hindustan Aeronautics | C8: HAL | E8: 4023.7 | F8: 66.88 | G8: 2690466 | H8: 114 | I8: 444714 | J8: 2245866 | L8: 328463 | M8: 12169.77 | N8: 8896.11 | P8: =J8/L8 -> 6.8375007 | Q8: 16.95 | R8: 30.24
B9: Bharat Dynamics | C9: BDL | E9: 1356.7 | F9: 36.66 | G9: 4965398 | H9: 12 | I9: 418164 | J9: 4547358 | L9: 37386 | M9: 469.7 | N9: 579.92 | P9: =J9/L9 -> 121.63264 | Q9: 52.19 | R9: 85.62
B10: Garden Reach Shipbuilders | C10: GRSE | E10: 2523.2 | F10: 11.46 | G10: 2892237 | H10: 320 | I10: 315730 | J10: 2579705 | L10: 65250 | M10: 756 | N10: 688.99 | P10: =J10/L10 -> 39.535709 | Q10: 26.37 | R10: 41.98
B11: Data Patterns | C11: DATAPATT | E11: 3491.2 | F11: 5.6 | G11: 1953988 | H11: 58 | I11: 17334 | J11: 1947235 | L11: 9761 | M11: 77.58 | N11: 247.07 | P11: =J11/L11 -> 199.49134 | Q11: 53.56 | R11: 78.35
B12: Zen Technologies | C12: ZENTEC | E12: 1426.8 | F12: 9.03 | G12: 1287713 | H12: 180 | I12: 83273 | J12: 1206235 | L12: 8346 | M12: 371.5 | N12: 284.44 | P12: =J12/L12 -> 144.52852 | Q12: 28.67 | R12: 49.09
B13: MTAR Technologies | C13: MTAR | E13: 3782.2 | F13: 3.08 | G13: 1163275 | H13: 1865 | I13: 17810 | J13: 1180139 | L13: 7532 | M13: 120.9 | N13: 65.19 | P13: =J13/L13 -> 156.68335 | Q13: 78.11 | R13: 171.37
B15: Average | P15: =AVERAGE(P8:P13) -> 111.45151 | Q15: =AVERAGE(Q8:Q13) -> 42.641667 | R15: =AVERAGE(R8:R13) -> 76.108333
B16: Median | P16: =MEDIAN(P8:P13) -> 133.08058 | Q16: =MEDIAN(Q8:Q13) -> 40.43 | R16: =MEDIAN(R8:R13) -> 63.72
B18: Bharat Electronics | C18: BEL | E18: 468.45 | F18: 730.98 | G18: 3424265 | H18: 589 | I18: 8911 | J18: 3343689 | L18: 265352 | M18: 2117 | N18: 5962.93 | P18: =J18/L18 -> 12.600956 | Q18: =J18/M18 -> 1579.4469 | R18: 57.4
B20: Metric | C20: Comps | E20: EV | F20: Net Debt | G20: Equity Value | H20: Shares | I20: Share Price | J20: Recommendation
B21: EV/Revenue | C21: =P16 -> 133.08058 | E21: =J18 -> 3343689 | F21: =H18-I18 -> -8322 | G21: =E21-F21 -> 3352011 | H21: =$F$18 -> 730.98 | I21: =G21/H21 -> 4585.6398 | J21: BUY
B22: EV/EBITDA | C22: =Q16 -> 40.43 | E22: =C22*M18 -> 85590.31 | F22: -8322 | G22: =E22-F22 -> 93912.31 | H22: =$F$18 -> 730.98 | I22: =G22/H22 -> 128.47453 | J22: BUY
B23: P/E | C23: =R16 -> 63.72 | E23: =F23+G23 -> 371635.9 | F23: -8322 | G23: =C23*N18 -> 379957.9 | H23: =$F$18 -> 730.98 | I23: =G23/H23 -> 519.79247 | J23: BUY
G28: 9

Sheet WACC
C1: Bharat Electronics Ltd
B3: Weighted-Average Cost of Capital (WACC)
B4: All Amounts Denominated in INR MM Unless Otherwise Stated
B7: Comparable Companies Beta
I8: Equity | J8: Total | K8: Debt/ | L8: Debt/ | M8: Tax | N8: Levered | O8: Unlevered
I9: Value | J9: Debt | K9: Equity | L9: Capital | M9: Rate % | N9: Beta | O9: Beta
B10: Hindustan Aeronautics | I10: ='Comps valution'!G8 -> 2690466 | J10: ='Comps valution'!H8 -> 114 | K10: =J10/I10 -> 4.2371842e-05 | L10: =J10/(I10+J10) -> 4.2370047e-05 | M10: 0.255 | N10: 0.002 | O10: 1.05
B11: Bharat Dynamics | I11: ='Comps valution'!G9 -> 4965398 | J11: ='Comps valution'!H9 -> 12 | K11: =J11/I11 -> 2.4167247e-06 | L11: =J11/(I11+J11) -> 2.4167189e-06 | M11: 0.258 | N11: 0.001 | O11: 0.85
B12: Garden Reach Shipbuilders | I12: ='Comps valution'!G10 -> 2892237 | J12: ='Comps valution'!H10 -> 320 | K12: 0.1 | L12: =J12/(I12+J12) -> 0.00011062876 | M12: 0.259 | N12: 0.001 | O12: 0.9
B13: Data Patterns | I13: ='Comps valution'!G11 -> 1953988 | J13: ='Comps valution'!H11 -> 58 | K13: 0.1 | L13: =J13/(I13+J13) -> 2.9682003e-05 | M13: 0.254 | N13: 0.012 | O13: 1.19
B14: Zen Technologies | I14: ='Comps valution'!G12 -> 1287713 | J14: ='Comps valution'!H12 -> 180 | K14: 0.1 | L14: =J14/(I14+J14) -> 0.00013976316 | M14: 0.259 | N14: 0.006 | O14: 0.75
B15: MTAR Technologies | I15: ='Comps valution'!G13 -> 1163275 | J15: ='Comps valution'!H13 -> 1865 | K15: 0.25 | L15: =J15/(I15+J15) -> 0.001600666 | M15: 0.255 | N15: 0.015 | O15: 0.79
B17: Average | K17: =AVERAGE(K10:K15) -> 0.091674131 | L17: =AVERAGE(L10:L15) -> 0.00032092112 | M17: =AVERAGE(M10:M15) -> 0.25666667 | N17: =AVERAGE(N10:N15) -> 0.0061666667 | O17: =AVERAGE(O10:O15) -> 0.92166667
B18: Median | K18: =MEDIAN(K10:K15) -> 0.1 | L18: =MEDIAN(L10:L15) -> 7.6499404e-05 | M18: =MEDIAN(M10:M15) -> 0.2565 | N18: =MEDIAN(N10:N15) -> 0.004 | O18: =MEDIAN(O10:O15) -> 0.875
B20: Hindustan Aeronautics Limited | I20: ='Comps valution'!G18 -> 3424265 | J20: ='Comps valution'!H18 -> 589
B22: WACC Calculation
B24: Target Capital Structure
B26: Proportion of Debt | G26: =L18 -> 7.6499404e-05
B27: Proportion of Equity | G27: =1-G26 -> 0.9999235
B29: Current Capital Structure
B30: Market Cap | G30: =I20 -> 3424265
B31: Total Debt | G31: =J20 -> 589
B32: Debt / Equity | G32: 0.0002
B34: Cost of Debt
B35: Pre-Tax Cost of Debt | G35: 0.0819
B36: Tax Rate | G36: 0.255
B37: After-Tax Cost of Debt | G37: 0.061
B39: Cost of Equity (CAPM)
B40: Risk Free Rate | G40: 0.0719
B41: Equity Market Return | G41: 0.135
B42: Equity Risk Premium | G42: 0.0631
B43: Unlevered Beta (median comps) | G43: =N17 -> 0.0061666667
B44: Levered Beta (re-levered) | G44: =O17 -> 0.92166667
B45: Cost of Equity | G45: 0.1271
B48: WACC
B49: Weighted Average Cost of Capital | G49: =(G45*99.98%)+(WACC!G37*(1-WACC!G36)*0.02%) -> 0.12708367

Sheet Sheet1

Sheet Forecasts & support schedules
B1: Bharat Electronics Ltd
A3: Financial Statements & DCF Analysis | D3: HISTORICAL PERIOD | I3: FORECASTED PERIOD
D5: ='Historical CF'!F3 -> 44286 | E5: ='Historical CF'!G3 -> 44651 | F5: ='Historical CF'!H3 -> 45016 | G5: ='Historical CF'!I3 -> 45382 | H5: ='Historical CF'!J3 -> 45747 | I5: 46221 | J5: 46587 | K5: 46954 | L5: 47320 | M5: 47686 | N5: 48052 | O5: 48418 | P5: 48784 | Q5: 49150 | R5: 49516
B6: Master Check
A8: Ratios & Assumptions
B10: LIVE SCENARIO
B11: Revenue Growth | C11: % | E11: =E27/D27-1 -> 0.088875505 | F11: =F27/E27-1 -> 0.15231008 | G11: =G27/F27-1 -> 0.14298773 | H11: =H27/G27-1 -> 0.17296606 | I11: =Assumptions!AO12 -> 0.18 | J11: =Assumptions!AP12 -> 0.17 | K11: =Assumptions!AQ12 -> 0.17 | L11: =Assumptions!AR12 -> 0.16 | M11: =Assumptions!AS12 -> 0.15 | N11: =Assumptions!AT12 -> 0.145 | O11: =Assumptions!AU12 -> 0.14 | P11: =Assumptions!AV12 -> 0.135 | ... R11: =Assumptions!AX12 -> 0.125
B12: Cost of Goods Sold (% of Revenue) | C12: % | D12: =-D28/D27 -> 0.57222961 | E12: =-E28/E27 -> 0.6155771 | F12: =-F28/F27 -> 0.60090784 | G12: =-G28/G27 -> 0.57944489 | H12: =-H28/H27 -> 0.58342354 | I12: =AVERAGE(F12:H12) -> 0.58792543 | J12: =I12 -> 0.58792543 | K12: =J12 -> 0.58792543 | L12: =K12 -> 0.58792543 | M12: =L12 -> 0.58792543 | N12: =M12 -> 0.58792543 | O12: =N12 -> 0.58792543 | P12: =O12 -> 0.58792543 | Q12: =P12 -> 0.58792543 | R12: =Q12 -> 0.58792543
B13: Salaries and benefits (% of Revenue) | C13: % | D13: =-D31/D27 -> 0.13799086 | E13: =-E31/E27 -> 0.13774475 | F13: =-F31/F27 -> 0.13021104 | G13: =-G31/G27 -> 0.12229919 | H13: =-H31/H27 -> 0.11557861 | I13: =H13 -> 0.11557861 | J13: =I13 -> 0.11557861 | K13: =J13 -> 0.11557861 | L13: =K13 -> 0.11557861 | M13: =L13 -> 0.11557861 | N13: =M13 -> 0.11557861 | O13: =N13 -> 0.11557861 | P13: =O13 -> 0.11557861 | ... R13: =Q13 -> 0.11557861
B14: Other operating Expenses (% of Revenue) | C14: % | D14: =-D22/D27 -> -4.0233353e-06 | E14: =-E22/E27 -> -3.985064e-06 | F14: =-F22/F27 -> -3.7115254e-06 | G14: =-G22/G27 -> -3.586196e-06 | H14: =-H22/H27 -> -3.1205824e-06 | I14: =H14 -> -3.1205824e-06 | J14: =I14 -> -3.1205824e-06 | K14: =J14 -> -3.1205824e-06 | L14: =K14 -> -3.1205824e-06 | M14: =L14 -> -3.1205824e-06 | N14: =M14 -> -3.1205824e-06 | O14: =N14 -> -3.1205824e-06 | P14: =O14 -> -3.1205824e-06 | ... R14: =Q14 -> -3.1205824e-06
B15: Depreciation & Amortization Expenses (% of PP&E) | C15: % | D15: =-D34/D27 -> 0.02604767 | E15: =-E34/E27 -> 0.024826039 | F15: =-F34/F27 -> 0.023113758 | G15: =-G34/G27 -> 0.020448313 | H15: =-H34/H27 -> 0.018411523 | I15: =H15+1% -> 0.028411523 | J15: =I15 -> 0.028411523 | K15: =J15+1% -> 0.038411523 | L15: =K15 -> 0.038411523 | M15: =L15+1% -> 0.048411523 | N15: =M15 -> 0.048411523 | O15: =N15+1% -> 0.058411523 | P15: =O15 -> 0.058411523 | Q15: =P15+1% -> 0.068411523 | R15: =Q15 -> 0.068411523
B16: Interest (% of revenue) | C16: % | D16: =-D36/D27 -> 0.00043231467 | E16: =-E36/E27 -> 0.00031670863 | F16: =-F36/F27 -> 0.00083814079 | G16: =-G36/G27 -> 0.00034805217 | H16: =-H36/H27 -> 0.00040620492 | I16: =H16 -> 0.00040620492 | J16: =I16 -> 0.00040620492 | K16: =J16 -> 0.00040620492 | L16: =K16 -> 0.00040620492 | M16: =L16 -> 0.00040620492 | N16: =M16 -> 0.00040620492 | O16: =N16 -> 0.00040620492 | P16: =O16 -> 0.00040620492 | ... R16: =Q16 -> 0.00040620492
B17: Other Income (Expenses) (% of Revenue) | C17: % | D17: =D37/D27 -> 0.0089662631 | E17: =E37/E27 -> 0.015253602 | F17: =F37/F27 -> 0.020402126 | G17: =G37/G27 -> 0.037474609 | H17: =H37/H27 -> 0.032445248 | I17: =H17 -> 0.032445248 | J17: =I17 -> 0.032445248 | K17: =J17 -> 0.032445248 | L17: =K17 -> 0.032445248 | M17: =L17 -> 0.032445248 | N17: =M17 -> 0.032445248 | O17: =N17 -> 0.032445248 | P17: =O17 -> 0.032445248 | ... R17: =Q17 -> 0.032445248
B18: Tax Rate (% of Earnings before Tax) | C18: % | D18: =D45/D27 -> 0 | E18: =E45/E27 -> 0 | F18: =F45/F27 -> 0 | G18: =G45/G27 -> 0 | H18: =H45/H27 -> 0 | I18: =H18 -> 0 | J18: =I18 -> 0 | K18: =J18 -> 0 | L18: =K18 -> 0 | M18: =L18 -> 0 | N18: =M18 -> 0 | O18: =N18 -> 0 | P18: =O18 -> 0 | ... R18: =Q18 -> 0
B20: Inventory | C20: Days | D20: =-D70/D28*365 -> 225.31949 | E20: =-E70/E28*365 -> 216.51499 | F20: =-F70/F28*365 -> 221.95325 | G20: =-G70/G28*365 -> 232.57493 | H20: =-H70/H28*365 -> 241.14428 | I20: =H20 -> 241.14428 | J20: =I20 -> 241.14428 | K20: =J20 -> 241.14428 | L20: =K20 -> 241.14428 | M20: =L20 -> 241.14428 | N20: =M20 -> 241.14428 | O20: =N20 -> 241.14428 | P20: =O20 -> 241.14428 | ... R20: =Q20 -> 241.14428
B21: Accounts Payable | C21: Days | D21: =-D116/D28*365 -> 149.61946 | E21: =E116/E27 -> 0.22001781 | F21: =F116/F27 -> 0.18873072 | G21: =G116/G27 -> 0.18375915 | H21: =H116/H27 -> 0.14112641 | I21: =H21 -> 0.14112641 | J21: =I21 -> 0.14112641 | K21: =J21 -> 0.14112641 | L21: =K21 -> 0.14112641 | M21: =L21 -> 0.14112641 | N21: =M21 -> 0.14112641 | O21: =N21 -> 0.14112641 | P21: =O21 -> 0.14112641 | ... R21: =Q21 -> 0.14112641
B22: Capital Asset Turnover Ratio | C22: Times | D22: =D27/D51 -> 5.6583504 | E22: =E27/E51 -> 6.1026313 | F22: =F27/F51 -> 6.549432 | G22: =G27/G51 -> 7.2331386 | H22: =H27/H51 -> 7.382677 | I22: =H22+0.5 -> 7.882677 | J22: =I22+0.5 -> 8.382677 | K22: =J22+0.5 -> 8.882677 | L22: =K22+0.5 -> 9.382677 | M22: =L22+0.5 -> 9.882677 | N22: =M22+0.5 -> 10.382677 | O22: =N22+0.5 -> 10.882677 | P22: =O22+0.5 -> 11.382677 | ... R22: =Q22+0.5 -> 12.382677
A25: Income Statement
A26: INCOME
B27: Revenue | D27: ='Historial IS'!K4 -> 1406383 | E27: ='Historial IS'!L4 -> 1531376 | F27: ='Historial IS'!M4 -> 1764620 | G27: ='Historial IS'!N4 -> 2016939 | H27: ='Historial IS'!O4 -> 2365801 | I27: =H27*(I11+1) -> 2791645.2 | J27: =I27*(J11+1) -> 3266224.9 | K27: =J27*(K11+1) -> 3821483.1 | L27: =K27*(L11+1) -> 4432920.4 | M27: =L27*(M11+1) -> 5097858.4 | N27: =M27*(N11+1) -> 5837047.9 | O27: =N27*(O11+1) -> 6654234.6 | P27: =O27*(P11+1) -> 7552556.3 | ... R27: =Q27*(R11+1) -> 9601187.2
B28: Cost of Good Sold (COGS) | D28: ='Historial IS'!K9+'Historial IS'!K10+'Historial IS'!K11 -> -804774 | E28: ='Historial IS'!L9+'Historial IS'!L10+'Historial IS'!L11 -> -942680 | F28: ='Historial IS'!M9+'Historial IS'!M10+'Historial IS'!M11 -> -1060374 | G28: ='Historial IS'!N9+'Historial IS'!N10+'Historial IS'!N11 -> -1168705 | H28: ='Historial IS'!O9+'Historial IS'!O10+'Historial IS'!O11 -> -1380264 | I28: =H28*I12 -> -811492.3 | J28: =I28*J12 -> -477096.96 | K28: =J28*K12 -> -280497.43 | L28: =K28*L12 -> -164911.57 | M28: =L28*M12 -> -96955.706 | N28: =M28*N12 -> -57002.725 | O28: =N28*O12 -> -33513.351 | P28: =O28*P12 -> -19703.351 | ... R28: =Q28*R12 -> -6810.5876
B29: Gross Profit | D29: =SUM(D27:D28) -> 601609 | E29: =SUM(E27:E28) -> 588696 | F29: =SUM(F27:F28) -> 704246 | G29: =SUM(G27:G28) -> 848234 | H29: =SUM(H27:H28) -> 985537 | I29: =SUM(I27:I28) -> 1980152.9 | J29: =SUM(J27:J28) -> 2789127.9 | K29: =SUM(K27:K28) -> 3540985.7 | ... R29: =SUM(R27:R28) -> 9594376.6
A30: EXPENSES
B31: Salaries and benefits | C31: ₹ MM | D31: ='Historial IS'!K12 -> -194068 | E31: ='Historial IS'!L12 -> -210939 | F31: ='Historial IS'!M12 -> -229773 | G31: ='Historial IS'!N12 -> -246670 | H31: ='Historial IS'!O12 -> -273436 | I31: =I27*I13 -> 322654.48 | J31: =J27*J13 -> 377505.74 | K31: =K27*K13 -> 441681.72 | L31: =L27*L13 -> 512350.79 | M31: =M27*M13 -> 589203.41 | N31: =N27*N13 -> 674637.91 | O31: =O27*O13 -> 769087.21 | P31: =P27*P13 -> 872913.99 | ... R31: =R27*R13 -> 1109691.9
B32: Other operating Expenses | C32: ₹ MM | D32: ='Historial IS'!K15 -> -111421 | E32: ='Historial IS'!L15 -> -99263 | F32: ='Historial IS'!M15 -> -149211 | G32: ='Historial IS'!N15 -> -213861 | H32: ='Historial IS'!O15 -> -197508 | I32: =H32*I14 -> 0.61633999 | J32: =I32*J14 -> -1.9233398e-06 | K32: =J32*K14 -> 6.0019402e-12 | L32: =K32*L14 -> -1.8729549e-17 | M32: =L32*M14 -> 5.8447102e-23 | N32: =M32*N14 -> -1.82389e-28 | O32: =N32*O14 -> 5.6915991e-34 | P32: =O32*P14 -> -1.7761104e-39 | ... R32: =Q32*R14 -> -1.7295825e-50
B33: EBITDA | C33: ₹ MM | D33: =SUM(D29,D31:D32) -> 296120 | E33: =SUM(E29,E31:E32) -> 278494 | F33: =SUM(F29,F31:F32) -> 325262 | G33: =SUM(G29,G31:G32) -> 387703 | H33: =SUM(H29,H31:H32) -> 514593 | I33: =SUM(I29,I31:I32) -> 2302808 | J33: =SUM(J29,J31:J32) -> 3166633.6 | K33: =SUM(K29,K31:K32) -> 3982667.4 | ... R33: =SUM(R29,R31:R32) -> 10704069
B34: Depreciation & Amortization Expenses | C34: ₹ MM | D34: ='Historial IS'!K14 -> -36633 | E34: ='Historial IS'!L14 -> -38018 | F34: ='Historial IS'!M14 -> -40787 | G34: ='Historial IS'!N14 -> -41243 | H34: ='Historial IS'!O14 -> -43558 | I34: =H34*I15 -> -1237.5491 | J34: =I34*J15 -> -35.160656 | K34: =J34*K15 -> -1.3505743 | L34: =K34*L15 -> -0.051877618 | M34: =L34*M15 -> -0.0025114745 | N34: =M34*N15 -> -0.00012158431 | O34: =N34*O15 -> -7.1019245e-06 | P34: =O34*P15 -> -4.1483423e-07 | ... R34: =Q34*R15 -> -1.9414808e-09
B35: EBIT | C35: ₹ MM | D35: =SUM(D33:D34) -> 259487 | E35: =SUM(E33:E34) -> 240476 | F35: =SUM(F33:F34) -> 284475 | G35: =SUM(G33:G34) -> 346460 | H35: =SUM(H33:H34) -> 471035 | I35: =SUM(I33:I34) -> 2301570.4 | J35: =SUM(J33:J34) -> 3166598.5 | K35: =SUM(K33:K34) -> 3982666 | ... R35: =SUM(R33:R34) -> 10704069
B36: Interest | C36: ₹ MM | D36: ='Historial IS'!K13 -> -608 | E36: ='Historial IS'!L13 -> -485 | F36: ='Historial IS'!M13 -> -1479 | G36: ='Historial IS'!N13 -> -702 | H36: ='Historial IS'!O13 -> -961 | I36: =H36*I16 -> -0.39036293 | J36: =I36*J16 -> -0.00015856734 | K36: =J36*K16 -> -6.4410833e-08 | L36: =K36*L16 -> -2.6163997e-11 | M36: =L36*M16 -> -1.0627944e-14 | N36: =M36*N16 -> -4.3171232e-18 | O36: =N36*O16 -> -1.7536367e-21 | P36: =O36*P16 -> -7.1233585e-25 | ... R36: =Q36*R16 -> -1.1753715e-31
B37: Other Income (Expenses) | C37: ₹ MM | D37: ='Historial IS'!K5 -> 12610 | E37: ='Historial IS'!L5 -> 23359 | F37: ='Historial IS'!M5 -> 36002 | G37: ='Historial IS'!N5 -> 75584 | H37: ='Historial IS'!O5 -> 76759 | I37: =H37*I17 -> 2490.4648 | J37: =I37*J17 -> 80.803747 | K37: =J37*K17 -> 2.6216976 | L37: =K37*L17 -> 0.085061629 | M37: =L37*M17 -> 0.0027598457 | N37: =M37*N17 -> 8.9543876e-05 | O37: =N37*O17 -> 2.9052733e-06 | P37: =O37*P17 -> 9.4262312e-08 | ... R37: =Q37*R17 -> 9.922938e-11
B38: Earnings before Tax | C38: ₹ MM | D38: =SUM(D35:D37) -> 271489 | E38: =SUM(E35:E37) -> 263350 | F38: =SUM(F35:F37) -> 318998 | G38: =SUM(G35:G37) -> 421342 | H38: =SUM(H35:H37) -> 546833 | I38: =SUM(I35:I37) -> 2304060.5 | J38: =SUM(J35:J37) -> 3166679.3 | K38: =SUM(K35:K37) -> 3982668.6 | ... R38: =SUM(R35:R37) -> 10704069
B39: Taxes | C39: ₹ MM | D39: ='Historial IS'!K26 -> -78047 | E39: ='Historial IS'!L26 -> -101217 | F39: ='Historial IS'!M26 -> -77071 | G39: ='Historial IS'!N26 -> -158462 | H39: ='Historial IS'!O26 -> -172096 | I39: =H39*I18 -> 0 | J39: =I39*J18 -> 0 | K39: =J39*K18 -> 0 | L39: =K39*L18 -> 0 | M39: =L39*M18 -> 0 | N39: =M39*N18 -> 0 | O39: =N39*O18 -> 0 | P39: =O39*P18 -> 0 | ... R39: =Q39*R18 -> 0
B40: Net income without jv | C40: ₹ MM | D40: =D38+D39 -> 193442 | E40: =E38+E39 -> 162133 | F40: =F38+F39 -> 241927 | G40: =G38+G39 -> 262880 | H40: =H38+H39 -> 374737 | I40: =I38+I39 -> 2304060.5 | J40: =J38+J39 -> 3166679.3 | K40: =K38+K39 -> 3982668.6 | ... R40: =R38+R39 -> 10704069
B41: Net profit from jv | C41: ₹ MM | D41: 0 | E41: 0 | F41: 0 | G41: 0 | H41: 0 | I41: 0 | J41: 0 | K41: 0 | L41: 0 | M41: 0 | N41: 0 | O41: 0 | P41: 0 | Q41: 0 | R41: 0
B42: Net income from continuing operations | C42: ₹ MM | D42: =SUM(D40:D41) -> 193442 | E42: =SUM(E40:E41) -> 162133 | F42: =SUM(F40:F41) -> 241927 | G42: =SUM(G40:G41) -> 262880 | H42: =SUM(H40:H41) -> 374737 | I42: =SUM(I40:I41) -> 2304060.5 | J42: =SUM(J40:J41) -> 3166679.3 | K42: =SUM(K40:K41) -> 3982668.6 | ... R42: =SUM(R40:R41) -> 10704069
B43: Net income from discontinuing operations | C43: ₹ MM | D43: 0 | E43: 0 | F43: 0 | G43: 0 | H43: 0 | I43: 0 | J43: 0 | K43: 0 | L43: 0 | M43: 0 | N43: 0 | O43: 0 | P43: 0 | Q43: 0 | R43: 0
B44: Total net earnings | D44: =SUM(D42:D43) -> 193442 | E44: =SUM(E42:E43) -> 162133 | F44: =SUM(F42:F43) -> 241927 | G44: =SUM(G42:G43) -> 262880 | H44: =SUM(H42:H43) -> 374737 | I44: =I42+I43 -> 2304060.5 | J44: =J42+J43 -> 3166679.3 | K44: =K42+K43 -> 3982668.6 | L44: =L42+L43 -> 4780359.6 | M44: =M42+M43 -> 5590106.1 | N44: =N42+N43 -> 6454683.1 | O44: =O42+O43 -> 7389808.5 | P44: =P42+P43 -> 8405766.9 | ... R44: =R42+R43 -> 10704069
B45: dividend | C45: ₹ MM | D45: 0 | E45: 0 | F45: 0 | G45: 0 | H45: 0 | I45: 0 | J45: 0 | K45: 0 | L45: 0 | M45: 0 | N45: 0 | O45: 0 | P45: 0 | Q45: 0 | R45: 0
B46: Retained earnings | C46: ₹ MM | D46: 0 | E46: 0 | F46: 0 | G46: 0 | H46: 0 | I46: 0 | J46: 0 | K46: 0 | L46: 0 | M46: 0 | N46: 0 | O46: 0 | P46: 0 | Q46: 0 | R46: 0
A48: Balance Sheet
B50: ='Historical BS'!B6 -> Non - current assets
B51: ='Historical BS'!B7 -> ( a ) Property , Plant and Equipment | D51: ='Historical BS'!K7 -> 248550 | E51: ='Historical BS'!L7 -> 250937 | F51: ='Historical BS'!M7 -> 269431 | G51: ='Historical BS'!N7 -> 278847 | H51: ='Historical BS'!O7 -> 320453
B52: ='Historical BS'!B8 -> ( b ) Capital work - in - progress | D52: ='Historical BS'!K8 -> 39747 | E52: ='Historical BS'!L8 -> 44593 | F52: ='Historical BS'!M8 -> 36123 | G52: ='Historical BS'!N8 -> 45642 | H52: ='Historical BS'!O8 -> 47698
B53: ='Historical BS'!B9 -> ( c ) Investment Property | D53: ='Historical BS'!K9 -> 8 | E53: ='Historical BS'!L9 -> 7 | F53: ='Historical BS'!M9 -> 6 | G53: ='Historical BS'!N9 -> 4 | H53: ='Historical BS'!O9 -> 4
B54: ='Historical BS'!B10 -> ( d ) Goodwill | D54: ='Historical BS'!K10 -> 0 | E54: ='Historical BS'!L10 -> 0 | F54: ='Historical BS'!M10 -> 0 | G54: ='Historical BS'!N10 -> 0 | H54: ='Historical BS'!O10 -> 0
B55: ='Historical BS'!B11 -> ( e ) Other Intangible assets | D55: ='Historical BS'!K11 -> 16656 | E55: ='Historical BS'!L11 -> 16582 | F55: ='Historical BS'!M11 -> 26849 | G55: ='Historical BS'!N11 -> 24670 | H55: ='Historical BS'!O11 -> 21466
B56: ='Historical BS'!B12 -> ( f ) Intangible Assets under Development | D56: ='Historical BS'!K12 -> 48521 | E56: ='Historical BS'!L12 -> 56011 | F56: ='Historical BS'!M12 -> 49371 | G56: ='Historical BS'!N12 -> 43730 | H56: ='Historical BS'!O12 -> 57482
B57: ='Historical BS'!B13 -> ( g ) Investments accounted for using the Equity Method | D57: ='Historical BS'!K13 -> 18989 | E57: ='Historical BS'!L13 -> 23292 | F57: ='Historical BS'!M13 -> 20073 | G57: ='Historical BS'!N13 -> 15157 | H57: ='Historical BS'!O13 -> 16136
B58: ='Historical BS'!B14 -> ( h ) Financial Assets | D58: ='Historical BS'!K14 -> 0 | E58: ='Historical BS'!L14 -> 0 | F58: ='Historical BS'!M14 -> 0 | G58: ='Historical BS'!N14 -> 0 | H58: ='Historical BS'!O14 -> 0
B59: ='Historical BS'!B15 -> ( i ) Investments | D59: ='Historical BS'!K15 -> 111605 | E59: ='Historical BS'!L15 -> 133910 | F59: ='Historical BS'!M15 -> 44926 | G59: ='Historical BS'!N15 -> 53066 | H59: ='Historical BS'!O15 -> 58161
B60: ='Historical BS'!B16 -> ( ii ) Trade Receivables | D60: ='Historical BS'!K16 -> 0 | E60: ='Historical BS'!L16 -> 0 | F60: ='Historical BS'!M16 -> 0 | G60: ='Historical BS'!N16 -> 0 | H60: ='Historical BS'!O16 -> 0
B61: ='Historical BS'!B17 -> ( iii ) Contract Assets | D61: ='Historical BS'!K17 -> 0 | E61: ='Historical BS'!L17 -> 0 | F61: ='Historical BS'!M17 -> 0 | G61: ='Historical BS'!N17 -> 0 | H61: ='Historical BS'!O17 -> 0
B62: ='Historical BS'!B18 -> ( iv ) Loans | D62: ='Historical BS'!K18 -> 736 | E62: ='Historical BS'!L18 -> 728 | F62: ='Historical BS'!M18 -> 656 | G62: ='Historical BS'!N18 -> 703 | H62: ='Historical BS'!O18 -> 663
... B67: ='Historical BS'!B23 -> Total non - current assets | D67: ='Historical BS'!K23 -> 577636 | E67: ='Historical BS'!L23 -> 661687 | F67: ='Historical BS'!M23 -> 544343 | G67: ='Historical BS'!N23 -> 546370 | H67: ='Historical BS'!O23 -> 597398
B69: ='Historical BS'!B25 -> Current assets
B70: ='Historical BS'!B26 -> ( a ) Inventories | D70: ='Historical BS'!K26 -> 496798 | E70: ='Historical BS'!L26 -> 559190 | F70: ='Historical BS'!M26 -> 644804 | G70: ='Historical BS'!N26 -> 744689 | H70: ='Historical BS'!O26 -> 911898
B71: ='Historical BS'!B27 -> ( b ) Financial Assets | D71: ='Historical BS'!K27 -> 0 | E71: ='Historical BS'!L27 -> 0 | F71: ='Historical BS'!M27 -> 0 | G71: ='Historical BS'!N27 -> 0 | H71: ='Historical BS'!O27 -> 0
B72: ='Historical BS'!B28 -> ( i ) Investments | D72: ='Historical BS'!K28 -> 0 | E72: ='Historical BS'!L28 -> 0 | F72: ='Historical BS'!M28 -> 0 | G72: ='Historical BS'!N28 -> 0 | H72: ='Historical BS'!O28 -> 0
B73: ='Historical BS'!B29 -> ( ii ) Trade receivables | D73: ='Historical BS'!K29 -> 656199 | E73: ='Historical BS'!L29 -> 610809 | F73: ='Historical BS'!M29 -> 703348 | G73: ='Historical BS'!N29 -> 739238 | H73: ='Historical BS'!O29 -> 911637
B74: ='Historical BS'!B30 -> ( iii ) Contract Assets | D74: ='Historical BS'!K30 -> 0 | E74: ='Historical BS'!L30 -> 0 | F74: ='Historical BS'!M30 -> 0 | G74: ='Historical BS'!N30 -> 0 | H74: ='Historical BS'!O30 -> 0
B75: ='Historical BS'!B31 -> ( iv ) Cash and Cash Equivalents | D75: ='Historical BS'!K31 -> 304290 | E75: ='Historical BS'!L31 -> 130086 | F75: ='Historical BS'!M31 -> 394569 | G75: ='Historical BS'!N31 -> 120632 | H75: ='Historical BS'!O31 -> 71345
B76: ='Historical BS'!B32 -> Bank Balances other than Cash and Cash Equivalents | D76: ='Historical BS'!K32 -> 203086 | E76: ='Historical BS'!L32 -> 626288 | F76: ='Historical BS'!M32 -> 416589 | G76: ='Historical BS'!N32 -> 985027 | H76: ='Historical BS'!O32 -> 883165
B77: ='Historical BS'!B33 -> ( vi ) Loans | D77: ='Historical BS'!K33 -> 152 | E77: ='Historical BS'!L33 -> 148 | F77: ='Historical BS'!M33 -> 172 | G77: ='Historical BS'!N33 -> 141 | H77: ='Historical BS'!O33 -> 147
B78: ='Historical BS'!B34 -> ( vii ) Other Financial Assets | D78: ='Historical BS'!K34 -> 6066 | E78: ='Historical BS'!L34 -> 10254 | F78: ='Historical BS'!M34 -> 20342 | G78: ='Historical BS'!N34 -> 29440 | H78: ='Historical BS'!O34 -> 24133
B79: ='Historical BS'!B35 -> ( c ) Current Tax Assets ( Net ) | D79: ='Historical BS'!K35 -> 13364 | E79: ='Historical BS'!L35 -> 14474 | F79: ='Historical BS'!M35 -> 40314 | G79: ='Historical BS'!N35 -> 44961 | H79: ='Historical BS'!O35 -> 35362
B80: ='Historical BS'!B36 -> ( d ) Other Currents Assets | D80: ='Historical BS'!K36 -> 691376 | E80: ='Historical BS'!L36 -> 778122 | F80: ='Historical BS'!M36 -> 784636 | G80: ='Historical BS'!N36 -> 742170 | H80: ='Historical BS'!O36 -> 648101
B81: ='Historical BS'!B37 -> Total current assets | D81: ='Historical BS'!K37 -> 2371331 | E81: ='Historical BS'!L37 -> 2729371 | F81: ='Historical BS'!M37 -> 3004774 | G81: ='Historical BS'!N37 -> 3406298 | H81: ='Historical BS'!O37 -> 3485788
B84: ='Historical BS'!B40 -> Total Assets | D84: ='Historical BS'!K40 -> 2948967 | E84: ='Historical BS'!L40 -> 3391058 | F84: ='Historical BS'!M40 -> 3549198.1 | G84: ='Historical BS'!N40 -> 3952749.1 | H84: ='Historical BS'!O40 -> 4083186
B85: ='Historical BS'!B41 -> 0
B86: ='Historical BS'!B42 -> EQUITY AND LIABILITIES
B87: ='Historical BS'!B43 -> Equity
B88: ='Historical BS'!B44 -> ( a ) Equity Share capital | D88: ='Historical BS'!K44 -> 24366 | E88: ='Historical BS'!L44 -> 24366 | F88: ='Historical BS'!M44 -> 73098 | G88: ='Historical BS'!N44 -> 73098 | H88: ='Historical BS'!O44 -> 73098
B89: ='Historical BS'!B45 -> ( b ) Other Equity | D89: ='Historical BS'!K45 -> 1081592 | E89: ='Historical BS'!L45 -> 1204227 | F89: ='Historical BS'!M45 -> 1313065 | G89: ='Historical BS'!N45 -> 1559549 | H89: ='Historical BS'!O45 -> 1924291
B90: ='Historical BS'!B46 -> Equity attributable to owners of the parent | D90: ='Historical BS'!K46 -> 1105958 | E90: ='Historical BS'!L46 -> 1228593 | F90: ='Historical BS'!M46 -> 1386163 | G90: ='Historical BS'!N46 -> 1632647 | H90: ='Historical BS'!O46 -> 1997389
B91: ='Historical BS'!B47 -> Non - controlling interest | D91: ='Historical BS'!K47 -> 1499 | E91: ='Historical BS'!L47 -> 1634 | F91: ='Historical BS'!M47 -> 1775 | G91: ='Historical BS'!N47 -> 1792 | H91: ='Historical BS'!O47 -> 1894
B92: ='Historical BS'!B48 -> Total equity | D92: ='Historical BS'!K48 -> 1107457 | E92: ='Historical BS'!L48 -> 1230227 | F92: ='Historical BS'!M48 -> 1387938 | G92: ='Historical BS'!N48 -> 1634439 | H92: ='Historical BS'!O48 -> 1999283
B94: ='Historical BS'!B50 -> LIABILITIES
B95: ='Historical BS'!B51 -> Non - current liabilities
B96: ='Historical BS'!B52 -> ( a ) Financial Liabilities | D96: ='Historical BS'!K52 -> 0 | E96: ='Historical BS'!L52 -> 0 | F96: ='Historical BS'!M52 -> 0 | G96: ='Historical BS'!N52 -> 0 | H96: ='Historical BS'!O52 -> 0
B97: ='Historical BS'!B53 -> ( i ) Borrowings | D97: ='Historical BS'!K53 -> 0 | E97: ='Historical BS'!L53 -> 0 | F97: ='Historical BS'!M53 -> 0 | G97: ='Historical BS'!N53 -> 0 | H97: ='Historical BS'!O53 -> 0
B98: ='Historical BS'!B54 -> ( ia ) Lease Liabilities | D98: ='Historical BS'!K54 -> 117 | E98: ='Historical BS'!L54 -> 5151 | F98: ='Historical BS'!M54 -> 5942 | G98: ='Historical BS'!N54 -> 6025 | H98: ='Historical BS'!O54 -> 5869
B99: ='Historical BS'!B55 -> ( ii ) Trade payables | D99: ='Historical BS'!K55 -> 0 | E99: ='Historical BS'!L55 -> 0 | F99: ='Historical BS'!M55 -> 0 | G99: ='Historical BS'!N55 -> 0 | H99: ='Historical BS'!O55 -> 0
B100: ='Historical BS'!B56 -> A ) total outstanding dues of micro enterprises and small enterprises | D100: ='Historical BS'!K56 -> 0 | E100: ='Historical BS'!L56 -> 0 | F100: ='Historical BS'!M56 -> 0 | G100: ='Historical BS'!N56 -> 0 | H100: ='Historical BS'!O56 -> 0
B101: ='Historical BS'!B57 -> B ) total outstanding dues of creditors other than micro enterprises and small enterprises | D101: ='Historical BS'!K57 -> 29 | E101: ='Historical BS'!L57 -> 34 | F101: ='Historical BS'!M57 -> 37 | G101: ='Historical BS'!N57 -> 0 | H101: ='Historical BS'!O57 -> 0
B102: ='Historical BS'!B58 -> Sub Total - Trade payables | D102: ='Historical BS'!K58 -> 0 | E102: ='Historical BS'!L58 -> 0 | F102: ='Historical BS'!M58 -> 0 | G102: ='Historical BS'!N58 -> 0 | H102: ='Historical BS'!O58 -> 0
B103: ='Historical BS'!B59 -> ( iii ) Other Financial Liabilities | D103: ='Historical BS'!K59 -> 671 | E103: ='Historical BS'!L59 -> 2022 | F103: ='Historical BS'!M59 -> 473 | G103: ='Historical BS'!N59 -> 480 | H103: ='Historical BS'!O59 -> 1457
B104: ='Historical BS'!B60 -> ( b ) Provisions | D104: ='Historical BS'!K60 -> 141203 | E104: ='Historical BS'!L60 -> 180532 | F104: ='Historical BS'!M60 -> 84465 | G104: ='Historical BS'!N60 -> 96728 | H104: ='Historical BS'!O60 -> 90216
B105: ='Historical BS'!B61 -> ( c ) Deferred Tax Liabilities ( Net ) | D105: ='Historical BS'!K61 -> 36 | E105: ='Historical BS'!L61 -> 145 | F105: ='Historical BS'!M61 -> 289 | G105: ='Historical BS'!N61 -> 547 | H105: ='Historical BS'!O61 -> 952
B106: ='Historical BS'!B62 -> ( d ) Other Non - Current Liabilities | D106: ='Historical BS'!K62 -> 16499 | E106: ='Historical BS'!L62 -> 14843 | F106: ='Historical BS'!M62 -> 13395 | G106: ='Historical BS'!N62 -> 11776 | H106: ='Historical BS'!O62 -> 10155
B107: ='Historical BS'!B63 -> Total non - current liabilities | D107: ='Historical BS'!K63 -> 158555 | E107: ='Historical BS'!L63 -> 202727 | F107: ='Historical BS'!M63 -> 104601 | G107: ='Historical BS'!N63 -> 115556 | H107: ='Historical BS'!O63 -> 108649
B109: ='Historical BS'!B65 -> Current Liabilities
B110: ='Historical BS'!B66 -> ( a ) Financial liabilities | D110: ='Historical BS'!K66 -> 0 | E110: ='Historical BS'!L66 -> 0 | F110: ='Historical BS'!M66 -> 0 | G110: ='Historical BS'!N66 -> 0 | H110: ='Historical BS'!O66 -> 0
B111: ='Historical BS'!B67 -> ( i ) Borrowings | D111: ='Historical BS'!K67 -> 0 | E111: ='Historical BS'!L67 -> 0 | F111: ='Historical BS'!M67 -> 0 | G111: ='Historical BS'!N67 -> 0 | H111: ='Historical BS'!O67 -> 0
B112: ='Historical BS'!B68 -> ( ia ) Lease Liabilities | D112: ='Historical BS'!K68 -> 135 | E112: ='Historical BS'!L68 -> 119 | F112: ='Historical BS'!M68 -> 192 | G112: ='Historical BS'!N68 -> 226 | H112: ='Historical BS'!O68 -> 254
B113: ='Historical BS'!B69 -> ( ii ) Trade payables | D113: ='Historical BS'!K69 -> 0 | E113: ='Historical BS'!L69 -> 0 | F113: ='Historical BS'!M69 -> 0 | G113: ='Historical BS'!N69 -> 0 | H113: ='Historical BS'!O69 -> 0
B114: ='Historical BS'!B70 -> A ) total outstanding dues of micro enterprises and small enterprises | D114: ='Historical BS'!K70 -> 15343 | E114: ='Historical BS'!L70 -> 24844 | F114: ='Historical BS'!M70 -> 20754 | G114: ='Historical BS'!N70 -> 21306 | H114: ='Historical BS'!O70 -> 17777
B115: ='Historical BS'!B71 -> B ) total outstanding dues of creditors other than micro enterprises and small enterprises | D115: ='Historical BS'!K71 -> 314547 | E115: ='Historical BS'!L71 -> 312086 | F115: ='Historical BS'!M71 -> 312284 | G115: ='Historical BS'!N71 -> 349325 | H115: ='Historical BS'!O71 -> 316100
B116: ='Historical BS'!B72 -> Sub Total - Trade payables | D116: ='Historical BS'!K72 -> 329890 | E116: ='Historical BS'!L72 -> 336930 | F116: ='Historical BS'!M72 -> 333038 | G116: ='Historical BS'!N72 -> 370631 | H116: ='Historical BS'!O72 -> 333877
B117: ='Historical BS'!B73 -> ( iii ) Other Financial liabilities | D117: ='Historical BS'!K73 -> 95895 | E117: ='Historical BS'!L73 -> 96043 | F117: ='Historical BS'!M73 -> 129023 | G117: ='Historical BS'!N73 -> 131714 | H117: ='Historical BS'!O73 -> 136832
B118: ='Historical BS'!B74 -> ( b ) Other Current Liabilities | D118: ='Historical BS'!K74 -> 1220296 | E118: ='Historical BS'!L74 -> 1480907 | F118: ='Historical BS'!M74 -> 1529906 | G118: ='Historical BS'!N74 -> 1628984 | H118: ='Historical BS'!O74 -> 1428702
...

Sheet Ratio analysis
B1: Bharat Electronics Ltd
B3: Ratio analysis | C3: ='Forecasts & support schedules'!D5 -> 44286 | D3: ='Forecasts & support schedules'!E5 -> 44651 | E3: ='Forecasts & support schedules'!F5 -> 45016 | F3: ='Forecasts & support schedules'!G5 -> 45382 | G3: ='Forecasts & support schedules'!H5 -> 45747
C4: Historical | D4: Historical | E4: Historical | F4: Historical | G4: Historical
B5: Operational Ratios
B6: Quick Ratio | C6: =('Forecasts & support schedules'!D81-'Forecasts & support schedules'!D70)/'Forecasts & support schedules'!D124 -> 0.6356575 | D6: =('Forecasts & support schedules'!E81-'Forecasts & support schedules'!E70)/'Forecasts & support schedules'!E124 -> 0.63997165 | E6: =('Forecasts & support schedules'!F81-'Forecasts & support schedules'!F70)/'Forecasts & support schedules'!F124 -> 0.66494568 | F6: =('Forecasts & support schedules'!G81-'Forecasts & support schedules'!G70)/'Forecasts & support schedules'!G124 -> 0.67337024 | G6: =('Forecasts & support schedules'!H81-'Forecasts & support schedules'!H70)/'Forecasts & support schedules'!H124 -> 0.63036315
B7: Current Ratio | C7: ='Forecasts & support schedules'!D81/'Forecasts & support schedules'!D124 -> 0.8041226 | D7: ='Forecasts & support schedules'!E81/'Forecasts & support schedules'!E124 -> 0.80487299 | E7: ='Forecasts & support schedules'!F81/'Forecasts & support schedules'!F124 -> 0.84662579 | F7: ='Forecasts & support schedules'!G81/'Forecasts & support schedules'!G124 -> 0.86177185 | G7: ='Forecasts & support schedules'!H81/'Forecasts & support schedules'!H124 -> 0.85369317
B8: Interest Coverage Ratio | C8: =-'Forecasts & support schedules'!D35/'Forecasts & support schedules'!D36 -> 426.78783 | D8: =-'Forecasts & support schedules'!E35/'Forecasts & support schedules'!E36 -> 495.8268 | E8: =-'Forecasts & support schedules'!F35/'Forecasts & support schedules'!F36 -> 192.3428 | F8: =-'Forecasts & support schedules'!G35/'Forecasts & support schedules'!G36 -> 493.53276 | G8: =-'Forecasts & support schedules'!H35/'Forecasts & support schedules'!H36 -> 490.15088
B9: Fixed Asset Turnover | C9: ='Forecasts & support schedules'!D27/'Forecasts & support schedules'!D51 -> 5.6583504 | D9: ='Forecasts & support schedules'!E27/'Forecasts & support schedules'!E51 -> 6.1026313 | E9: ='Forecasts & support schedules'!F27/'Forecasts & support schedules'!F51 -> 6.549432 | F9: ='Forecasts & support schedules'!G27/'Forecasts & support schedules'!G51 -> 7.2331386 | G9: ='Forecasts & support schedules'!H27/'Forecasts & support schedules'!H51 -> 7.382677
B10: Cash Conversion Cycle | C10: ='Forecasts & support schedules'!D20-'Forecasts & support schedules'!D21 -> 75.700035 | D10: ='Forecasts & support schedules'!E20-'Forecasts & support schedules'!E21 -> 216.29497 | E10: ='Forecasts & support schedules'!F20-'Forecasts & support schedules'!F21 -> 221.76452 | F10: ='Forecasts & support schedules'!G20-'Forecasts & support schedules'!G21 -> 232.39117 | G10: ='Forecasts & support schedules'!H20-'Forecasts & support schedules'!H21 -> 241.00315
B11: Debt to Equity Ratio | C11: ='Forecasts & support schedules'!D97/'Forecasts & support schedules'!D91 -> 0 | D11: ='Forecasts & support schedules'!E97/'Forecasts & support schedules'!E91 -> 0 | E11: ='Forecasts & support schedules'!F97/'Forecasts & support schedules'!F91 -> 0 | F11: ='Forecasts & support schedules'!G97/'Forecasts & support schedules'!G91 -> 0 | G11: ='Forecasts & support schedules'!H97/'Forecasts & support schedules'!H91 -> 0
B14: Profitability Ratios
B15: Gross Margin (%) | C15: ='Forecasts & support schedules'!D29/'Forecasts & support schedules'!D27 -> 0.42777039 | D15: ='Forecasts & support schedules'!E29/'Forecasts & support schedules'!E27 -> 0.3844229 | E15: ='Forecasts & support schedules'!F29/'Forecasts & support schedules'!F27 -> 0.39909216 | F15: ='Forecasts & support schedules'!G29/'Forecasts & support schedules'!G27 -> 0.42055511 | G15: ='Forecasts & support schedules'!H29/'Forecasts & support schedules'!H27 -> 0.41657646
B16: Op Profit Margin (%) | C16: ='Forecasts & support schedules'!D35/'Forecasts & support schedules'!D27 -> 0.18450664 | D16: ='Forecasts & support schedules'!E35/'Forecasts & support schedules'!E27 -> 0.15703263 | E16: ='Forecasts & support schedules'!F35/'Forecasts & support schedules'!F27 -> 0.16121035 | F16: ='Forecasts & support schedules'!G35/'Forecasts & support schedules'!G27 -> 0.17177515 | G16: ='Forecasts & support schedules'!H35/'Forecasts & support schedules'!H27 -> 0.1991017
B17: Net Profit Margin (%) | C17: ='Forecasts & support schedules'!D44/'Forecasts & support schedules'!D27 -> 0.13754575 | D17: ='Forecasts & support schedules'!E44/'Forecasts & support schedules'!E27 -> 0.10587406 | E17: ='Forecasts & support schedules'!F44/'Forecasts & support schedules'!F27 -> 0.13709864 | F17: ='Forecasts & support schedules'!G44/'Forecasts & support schedules'!G27 -> 0.13033612 | G17: ='Forecasts & support schedules'!H44/'Forecasts & support schedules'!H27 -> 0.15839752
B18: ROCE (%) | C18: ='Forecasts & support schedules'!D35/('Forecasts & support schedules'!D84-'Forecasts & support schedules'!D107) -> 0.092992361 | D18: ='Forecasts & support schedules'!E35/('Forecasts & support schedules'!E84-'Forecasts & support schedules'!E107) -> 0.075423788 | E18: ='Forecasts & support schedules'!F35/('Forecasts & support schedules'!F84-'Forecasts & support schedules'!F107) -> 0.082585856 | F18: ='Forecasts & support schedules'!G35/('Forecasts & support schedules'!G84-'Forecasts & support schedules'!G107) -> 0.090289957 | G18: ='Forecasts & support schedules'!H35/('Forecasts & support schedules'!H84-'Forecasts & support schedules'!H107) -> 0.11851318
B21: Dupont Analysis
B23: Return on Assets (%) | C23: =C24*C25 -> 0.061022472 | D23: =D24*D25 -> 0.046722483 | E23: =E24*E25 -> 0.064497121 | F23: =F24*F25 -> 0.065426113 | G23: =G24*G25 -> 0.091775638
B24: Net Profit Margin (%) | C24: =C17 -> 0.13754575 | D24: =D17 -> 0.10587406 | E24: =E17 -> 0.13709864 | F24: =F17 -> 0.13033612 | G24: =G17 -> 0.15839752
B25: Asset Turnover ratio | C25: ='Forecasts & support schedules'!D27/AVERAGE('Forecasts & support schedules'!D84:E84) -> 0.44365219 | D25: ='Forecasts & support schedules'!E27/AVERAGE('Forecasts & support schedules'!E84:F84) -> 0.44130245 | E25: ='Forecasts & support schedules'!F27/AVERAGE('Forecasts & support schedules'!F84:G84) -> 0.47044319 | F25: ='Forecasts & support schedules'!G27/AVERAGE('Forecasts & support schedules'!G84:H84) -> 0.50197991 | G25: ='Forecasts & support schedules'!H27/AVERAGE('Forecasts & support schedules'!H84:I84) -> 0.57940074
B27: ROE (%) | C27: =C28*C29*C30 -> 0.13084085 | D27: =D28*D29*D30 -> 0.10379596 | E27: =E28*E29*E30 -> 0.13980987 | F27: =F28*F29*F30 -> 0.13650277 | G27: =G28*G29*G30 -> 0.1601643
B28: Net Profit Margin (%) | C28: =C24 -> 0.13754575 | D28: =D24 -> 0.10587406 | E28: =E24 -> 0.13709864 | F28: =F24 -> 0.13033612 | G28: =G24 -> 0.15839752
B29: Asset Turnover ratio | C29: =C25 -> 0.44365219 | D29: =D25 -> 0.44130245 | E29: =E25 -> 0.47044319 | F29: =F25 -> 0.50197991 | G29: =G25 -> 0.57940074
B30: Equity Multiplier | C30: ='Forecasts & support schedules'!D81/'Forecasts & support schedules'!D90 -> 2.144142 | D30: ='Forecasts & support schedules'!E81/'Forecasts & support schedules'!E90 -> 2.221542 | E30: ='Forecasts & support schedules'!F81/'Forecasts & support schedules'!F90 -> 2.1676917 | F30: ='Forecasts & support schedules'!G81/'Forecasts & support schedules'!G90 -> 2.0863653 | G30: ='Forecasts & support schedules'!H81/'Forecasts & support schedules'!H90 -> 1.7451723
B32: Valuation Ratios
B33: P/E | C33: 14.52x | D33: 21.42x | E33: 23.89x | F33: 36.96x | G33: 41.37x
B35: Price to Book | C35: 2.75x | D35: 4.18x | E35: 5.14x | F35: 9.01x | G35: 11.01x
B37: EV/EBITDA | C37: 9.27x | D37: 15.46x | E37: 17.45x | F37: 27.20x | G37: 31.13x

Sheet Common Size
B1: Bharat Electronics Ltd
A5: INCOME STATEMENT | D5: ='Ratio analysis'!C3 -> 44286 | E5: ='Ratio analysis'!D3 -> 44651 | F5: ='Ratio analysis'!E3 -> 45016 | G5: ='Ratio analysis'!F3 -> 45382 | H5: ='Ratio analysis'!G3 -> 45747
D6: Historical | E6: Historical | F6: Historical | G6: Historical | H6: Historical
A7: INCOME
B8: Revenue | D8: ='Forecasts & support schedules'!D27/'Forecasts & support schedules'!$D$27 -> 1 | E8: ='Forecasts & support schedules'!E27/'Forecasts & support schedules'!E27 -> 1 | F8: ='Forecasts & support schedules'!F27/'Forecasts & support schedules'!F27 -> 1 | G8: ='Forecasts & support schedules'!G27/'Forecasts & support schedules'!G27 -> 1 | H8: ='Forecasts & support schedules'!H27/'Forecasts & support schedules'!H27 -> 1
B9: Cost of Good Sold (COGS) | D9: ='Forecasts & support schedules'!D28/'Forecasts & support schedules'!$D$27 -> -0.57222961 | E9: ='Forecasts & support schedules'!E28/'Forecasts & support schedules'!E27 -> -0.6155771 | F9: ='Forecasts & support schedules'!F28/'Forecasts & support schedules'!F27 -> -0.60090784 | G9: ='Forecasts & support schedules'!G28/'Forecasts & support schedules'!G27 -> -0.57944489 | H9: ='Forecasts & support schedules'!H28/'Forecasts & support schedules'!H27 -> -0.58342354
B10: Gross Profit | D10: =D8+D9 -> 0.42777039 | E10: =E8+E9 -> 0.3844229 | F10: =F8+F9 -> 0.39909216 | G10: =G8+G9 -> 0.42055511 | H10: =H8+H9 -> 0.41657646
A11: EXPENSES
B12: Salaries and benefits | D12: ='Forecasts & support schedules'!D31/'Forecasts & support schedules'!D$28 -> 0.24114596 | E12: ='Forecasts & support schedules'!E31/'Forecasts & support schedules'!E$28 -> 0.22376522 | F12: ='Forecasts & support schedules'!F31/'Forecasts & support schedules'!F$28 -> 0.21669053 | G12: ='Forecasts & support schedules'!G31/'Forecasts & support schedules'!G$28 -> 0.21106267 | H12: ='Forecasts & support schedules'!H31/'Forecasts & support schedules'!H$28 -> 0.19810413
B13: Other operating Expenses | D13: ='Forecasts & support schedules'!D32/'Forecasts & support schedules'!D$28 -> 0.13845005 | E13: ='Forecasts & support schedules'!E32/'Forecasts & support schedules'!E$28 -> 0.10529872 | F13: ='Forecasts & support schedules'!F32/'Forecasts & support schedules'!F$28 -> 0.14071545 | G13: ='Forecasts & support schedules'!G32/'Forecasts & support schedules'!G$28 -> 0.18298972 | H13: ='Forecasts & support schedules'!H32/'Forecasts & support schedules'!H$28 -> 0.14309436
B14: EBITDA | D14: =D12+D13 -> 0.37959601 | E14: =E12+E13 -> 0.32906395 | F14: =F12+F13 -> 0.35740597 | G14: =G12+G13 -> 0.39405239 | H14: =H12+H13 -> 0.3411985
B15: Depreciation & Amortization Expenses | D15: ='Forecasts & support schedules'!D34/'Forecasts & support schedules'!D$27 -> -0.02604767 | E15: ='Forecasts & support schedules'!E34/'Forecasts & support schedules'!E$27 -> -0.024826039 | F15: ='Forecasts & support schedules'!F34/'Forecasts & support schedules'!F$27 -> -0.023113758 | G15: ='Forecasts & support schedules'!G34/'Forecasts & support schedules'!G$27 -> -0.020448313 | H15: ='Forecasts & support schedules'!H34/'Forecasts & support schedules'!H$27 -> -0.018411523
B16: EBIT | D16: =D14+D15 -> 0.35354834 | E16: =E14+E15 -> 0.30423791 | F16: =F14+F15 -> 0.33429221 | G16: =G14+G15 -> 0.37360408 | H16: =H14+H15 -> 0.32278697
B17: Interest | D17: ='Forecasts & support schedules'!D35/'Forecasts & support schedules'!D$27 -> 0.18450664 | E17: ='Forecasts & support schedules'!E35/'Forecasts & support schedules'!E$27 -> 0.15703263 | F17: ='Forecasts & support schedules'!F35/'Forecasts & support schedules'!F$27 -> 0.16121035 | G17: ='Forecasts & support schedules'!G35/'Forecasts & support schedules'!G$27 -> 0.17177515 | H17: ='Forecasts & support schedules'!H35/'Forecasts & support schedules'!H$27 -> 0.1991017
B18: Other Income (Expenses) | D18: ='Forecasts & support schedules'!D37/'Forecasts & support schedules'!D$27 -> 0.0089662631 | E18: ='Forecasts & support schedules'!E37/'Forecasts & support schedules'!E$27 -> 0.015253602 | F18: ='Forecasts & support schedules'!F37/'Forecasts & support schedules'!F$27 -> 0.020402126 | G18: ='Forecasts & support schedules'!G37/'Forecasts & support schedules'!G$27 -> 0.037474609 | H18: ='Forecasts & support schedules'!H37/'Forecasts & support schedules'!H$27 -> 0.032445248
B19: Earnings before Tax | D19: =D16-D17-D18 -> 0.16007544 | E19: =E16-E17-E18 -> 0.13195168 | F19: =F16-F17-F18 -> 0.15267974 | G19: =G16-G17-G18 -> 0.16435432 | H19: =H16-H17-H18 -> 0.091240025
B20: Taxes | D20: ='Forecasts & support schedules'!D39/'Forecasts & support schedules'!D$27 -> -0.05549484 | E20: ='Forecasts & support schedules'!E39/'Forecasts & support schedules'!E$27 -> -0.066095459 | F20: ='Forecasts & support schedules'!F39/'Forecasts & support schedules'!F$27 -> -0.043675692 | G20: ='Forecasts & support schedules'!G39/'Forecasts & support schedules'!G$27 -> -0.078565589 | H20: ='Forecasts & support schedules'!H39/'Forecasts & support schedules'!H$27 -> -0.072743227
B21: Net income without jv | D21: =D19+D20 -> 0.1045806 | E21: =E19+E20 -> 0.065856216 | F21: =F19+F20 -> 0.10900405 | G21: =G19+G20 -> 0.08578873 | H21: =H19+H20 -> 0.018496797
B22: Net profit from jv
B23: Net income from continuing operations | D23: ='Forecasts & support schedules'!D42/'Forecasts & support schedules'!D$27 -> 0.13754575 | E23: ='Forecasts & support schedules'!E42/'Forecasts & support schedules'!E$27 -> 0.10587406 | F23: ='Forecasts & support schedules'!F42/'Forecasts & support schedules'!F$27 -> 0.13709864 | G23: ='Forecasts & support schedules'!G42/'Forecasts & support schedules'!G$27 -> 0.13033612 | H23: ='Forecasts & support schedules'!H42/'Forecasts & support schedules'!H$27 -> 0.15839752
B24: Net income from discontinuing operations
B25: Total net earnings | D25: =D23 -> 0.13754575 | E25: =E23 -> 0.10587406 | F25: =F23 -> 0.13709864 | G25: =G23 -> 0.13033612 | H25: =H23 -> 0.15839752
B27: Balance sheet | D27: 2020 | E27: =D27+1 -> 2021 | F27: =E27+1 -> 2022 | G27: =F27+1 -> 2023 | H27: =G27+1 -> 2024
D28: Historical | E28: Historical | F28: Historical | G28: Historical | H28: Historical
B30: ='Forecasts & support schedules'!B50 -> Non - current assets
B31: ='Forecasts & support schedules'!B51 -> ( a ) Property , Plant and Equipment | D31: ='Forecasts & support schedules'!D51/'Forecasts & support schedules'!D$67 -> 0.43028828 | E31: ='Forecasts & support schedules'!E51/'Forecasts & support schedules'!E$67 -> 0.37923822 | F31: ='Forecasts & support schedules'!F51/'Forecasts & support schedules'!F$67 -> 0.49496549 | G31: ='Forecasts & support schedules'!G51/'Forecasts & support schedules'!G$67 -> 0.51036294 | H31: ='Forecasts & support schedules'!H51/'Forecasts & support schedules'!H$67 -> 0.53641458
B32: ='Forecasts & support schedules'!B52 -> ( b ) Capital work - in - progress | D32: ='Forecasts & support schedules'!D52/'Forecasts & support schedules'!D$67 -> 0.068809769 | E32: ='Forecasts & support schedules'!E52/'Forecasts & support schedules'!E$67 -> 0.067392891 | F32: ='Forecasts & support schedules'!F52/'Forecasts & support schedules'!F$67 -> 0.066360732 | G32: ='Forecasts & support schedules'!G52/'Forecasts & support schedules'!G$67 -> 0.083536797 | H32: ='Forecasts & support schedules'!H52/'Forecasts & support schedules'!H$67 -> 0.079842919
B33: ='Forecasts & support schedules'!B53 -> ( c ) Investment Property | D33: ='Forecasts & support schedules'!D53/'Forecasts & support schedules'!D$67 -> 1.3849552e-05 | E33: ='Forecasts & support schedules'!E53/'Forecasts & support schedules'!E$67 -> 1.057902e-05 | F33: ='Forecasts & support schedules'!F53/'Forecasts & support schedules'!F$67 -> 1.1022462e-05 | G33: ='Forecasts & support schedules'!G53/'Forecasts & support schedules'!G$67 -> 7.3210462e-06 | H33: ='Forecasts & support schedules'!H53/'Forecasts & support schedules'!H$67 -> 6.6957037e-06
B34: ='Forecasts & support schedules'!B54 -> ( d ) Goodwill | D34: ='Forecasts & support schedules'!D54/'Forecasts & support schedules'!D$67 -> 0 | E34: ='Forecasts & support schedules'!E54/'Forecasts & support schedules'!E$67 -> 0 | F34: ='Forecasts & support schedules'!F54/'Forecasts & support schedules'!F$67 -> 0 | G34: ='Forecasts & support schedules'!G54/'Forecasts & support schedules'!G$67 -> 0 | H34: ='Forecasts & support schedules'!H54/'Forecasts & support schedules'!H$67 -> 0
B35: ='Forecasts & support schedules'!B55 -> ( e ) Other Intangible assets | D35: ='Forecasts & support schedules'!D55/'Forecasts & support schedules'!D$67 -> 0.028834768 | E35: ='Forecasts & support schedules'!E55/'Forecasts & support schedules'!E$67 -> 0.025060187 | F35: ='Forecasts & support schedules'!F55/'Forecasts & support schedules'!F$67 -> 0.04932368 | G35: ='Forecasts & support schedules'!G55/'Forecasts & support schedules'!G$67 -> 0.045152552 | H35: ='Forecasts & support schedules'!H55/'Forecasts & support schedules'!H$67 -> 0.035932494
B36: ='Forecasts & support schedules'!B56 -> ( f ) Intangible Assets under Development | D36: ='Forecasts & support schedules'!D56/'Forecasts & support schedules'!D$67 -> 0.083999266 | E36: ='Forecasts & support schedules'!E56/'Forecasts & support schedules'!E$67 -> 0.084648784 | F36: ='Forecasts & support schedules'!F56/'Forecasts & support schedules'!F$67 -> 0.090698328 | G36: ='Forecasts & support schedules'!G56/'Forecasts & support schedules'!G$67 -> 0.080037337 | H36: ='Forecasts & support schedules'!H56/'Forecasts & support schedules'!H$67 -> 0.09622061
B37: ='Forecasts & support schedules'!B57 -> ( g ) Investments accounted for using the Equity Method | D37: ='Forecasts & support schedules'!D57/'Forecasts & support schedules'!D$67 -> 0.032873644 | E37: ='Forecasts & support schedules'!E57/'Forecasts & support schedules'!E$67 -> 0.035200933 | F37: ='Forecasts & support schedules'!F57/'Forecasts & support schedules'!F$67 -> 0.036875646 | G37: ='Forecasts & support schedules'!G57/'Forecasts & support schedules'!G$67 -> 0.027741274 | H37: ='Forecasts & support schedules'!H57/'Forecasts & support schedules'!H$67 -> 0.027010469
B38: ='Forecasts & support schedules'!B58 -> ( h ) Financial Assets | D38: ='Forecasts & support schedules'!D58/'Forecasts & support schedules'!D$67 -> 0 | E38: ='Forecasts & support schedules'!E58/'Forecasts & support schedules'!E$67 -> 0 | F38: ='Forecasts & support schedules'!F58/'Forecasts & support schedules'!F$67 -> 0 | G38: ='Forecasts & support schedules'!G58/'Forecasts & support schedules'!G$67 -> 0 | H38: ='Forecasts & support schedules'!H58/'Forecasts & support schedules'!H$67 -> 0
B39: ='Forecasts & support schedules'!B59 -> ( i ) Investments | D39: ='Forecasts & support schedules'!D59/'Forecasts & support schedules'!D$67 -> 0.19320991 | E39: ='Forecasts & support schedules'!E59/'Forecasts & support schedules'!E$67 -> 0.20237665 | F39: ='Forecasts & support schedules'!F59/'Forecasts & support schedules'!F$67 -> 0.082532521 | G39: ='Forecasts & support schedules'!G59/'Forecasts & support schedules'!G$67 -> 0.097124659 | H39: ='Forecasts & support schedules'!H59/'Forecasts & support schedules'!H$67 -> 0.097357206
B40: ='Forecasts & support schedules'!B60 -> ( ii ) Trade Receivables | D40: ='Forecasts & support schedules'!D60/'Forecasts & support schedules'!D$67 -> 0 | E40: ='Forecasts & support schedules'!E60/'Forecasts & support schedules'!E$67 -> 0 | F40: ='Forecasts & support schedules'!F60/'Forecasts & support schedules'!F$67 -> 0 | G40: ='Forecasts & support schedules'!G60/'Forecasts & support schedules'!G$67 -> 0 | H40: ='Forecasts & support schedules'!H60/'Forecasts & support schedules'!H$67 -> 0
B41: ='Forecasts & support schedules'!B61 -> ( iii ) Contract Assets | D41: ='Forecasts & support schedules'!D61/'Forecasts & support schedules'!D$67 -> 0 | E41: ='Forecasts & support schedules'!E61/'Forecasts & support schedules'!E$67 -> 0 | F41: ='Forecasts & support schedules'!F61/'Forecasts & support schedules'!F$67 -> 0 | G41: ='Forecasts & support schedules'!G61/'Forecasts & support schedules'!G$67 -> 0 | H41: ='Forecasts & support schedules'!H61/'Forecasts & support schedules'!H$67 -> 0
B42: ='Forecasts & support schedules'!B62 -> ( iv ) Loans | D42: ='Forecasts & support schedules'!D62/'Forecasts & support schedules'!D$67 -> 0.0012741588 | E42: ='Forecasts & support schedules'!E62/'Forecasts & support schedules'!E$67 -> 0.0011002181 | F42: ='Forecasts & support schedules'!F62/'Forecasts & support schedules'!F$67 -> 0.0012051225 | G42: ='Forecasts & support schedules'!G62/'Forecasts & support schedules'!G$67 -> 0.0012866739 | H42: ='Forecasts & support schedules'!H62/'Forecasts & support schedules'!H$67 -> 0.0011098129
... B46: ='Forecasts & support schedules'!B66 -> ( k ) Other Non - Current Assets | D46: ='Forecasts & support schedules'!D66/'Forecasts & support schedules'!D$67 -> 0.068674736 | E46: ='Forecasts & support schedules'!E66/'Forecasts & support schedules'!E$67 -> 0.10334493 | F46: ='Forecasts & support schedules'!F66/'Forecasts & support schedules'!F$67 -> 0.080655028 | G46: ='Forecasts & support schedules'!G66/'Forecasts & support schedules'!G$67 -> 0.046122591 | H46: ='Forecasts & support schedules'!H66/'Forecasts & support schedules'!H$67 -> 0.032534424
B47: ='Forecasts & support schedules'!B67 -> Total non - current assets | D47: =SUM(D31:D46) -> 1 | E47: =SUM(E31:E46) -> 1 | F47: =SUM(F31:F46) -> 1 | G47: =SUM(G31:G46) -> 1 | H47: =SUM(H31:H46) -> 1
B49: ='Forecasts & support schedules'!B69 -> Current assets
B50: ='Forecasts & support schedules'!B70 -> ( a ) Inventories | D50: ='Forecasts & support schedules'!D70/'Forecasts & support schedules'!D$81 -> 0.20950175 | E50: ='Forecasts & support schedules'!E70/'Forecasts & support schedules'!E$81 -> 0.20487871 | F50: ='Forecasts & support schedules'!F70/'Forecasts & support schedules'!F$81 -> 0.21459318 | G50: ='Forecasts & support schedules'!G70/'Forecasts & support schedules'!G$81 -> 0.21862121 | H50: ='Forecasts & support schedules'!H70/'Forecasts & support schedules'!H$81 -> 0.26160455
B51: ='Forecasts & support schedules'!B71 -> ( b ) Financial Assets | D51: ='Forecasts & support schedules'!D71/'Forecasts & support schedules'!D$81 -> 0 | E51: ='Forecasts & support schedules'!E71/'Forecasts & support schedules'!E$81 -> 0 | F51: ='Forecasts & support schedules'!F71/'Forecasts & support schedules'!F$81 -> 0 | G51: ='Forecasts & support schedules'!G71/'Forecasts & support schedules'!G$81 -> 0 | H51: ='Forecasts & support schedules'!H71/'Forecasts & support schedules'!H$81 -> 0
B52: ='Forecasts & support schedules'!B72 -> ( i ) Investments | D52: ='Forecasts & support schedules'!D72/'Forecasts & support schedules'!D$81 -> 0 | E52: ='Forecasts & support schedules'!E72/'Forecasts & support schedules'!E$81 -> 0 | F52: ='Forecasts & support schedules'!F72/'Forecasts & support schedules'!F$81 -> 0 | G52: ='Forecasts & support schedules'!G72/'Forecasts & support schedules'!G$81 -> 0 | H52: ='Forecasts & support schedules'!H72/'Forecasts & support schedules'!H$81 -> 0
B53: ='Forecasts & support schedules'!B73 -> ( ii ) Trade receivables | D53: ='Forecasts & support schedules'!D73/'Forecasts & support schedules'!D$81 -> 0.27672181 | E53: ='Forecasts & support schedules'!E73/'Forecasts & support schedules'!E$81 -> 0.22379112 | F53: ='Forecasts & support schedules'!F73/'Forecasts & support schedules'!F$81 -> 0.23407684 | G53: ='Forecasts & support schedules'!G73/'Forecasts & support schedules'!G$81 -> 0.21702094 | H53: ='Forecasts & support schedules'!H73/'Forecasts & support schedules'!H$81 -> 0.26152967
B54: ='Forecasts & support schedules'!B74 -> ( iii ) Contract Assets | D54: ='Forecasts & support schedules'!D74/'Forecasts & support schedules'!D$81 -> 0 | E54: ='Forecasts & support schedules'!E74/'Forecasts & support schedules'!E$81 -> 0 | F54: ='Forecasts & support schedules'!F74/'Forecasts & support schedules'!F$81 -> 0 | G54: ='Forecasts & support schedules'!G74/'Forecasts & support schedules'!G$81 -> 0 | H54: ='Forecasts & support schedules'!H74/'Forecasts & support schedules'!H$81 -> 0
B55: ='Forecasts & support schedules'!B75 -> ( iv ) Cash and Cash Equivalents | D55: ='Forecasts & support schedules'!D75/'Forecasts & support schedules'!D$81 -> 0.12832034 | E55: ='Forecasts & support schedules'!E75/'Forecasts & support schedules'!E$81 -> 0.047661531 | F55: ='Forecasts & support schedules'!F75/'Forecasts & support schedules'!F$81 -> 0.13131404 | G55: ='Forecasts & support schedules'!G75/'Forecasts & support schedules'!G$81 -> 0.0354144 | H55: ='Forecasts & support schedules'!H75/'Forecasts & support schedules'!H$81 -> 0.020467395
B56: ='Forecasts & support schedules'!B76 -> Bank Balances other than Cash and Cash Equivalents | D56: ='Forecasts & support schedules'!D76/'Forecasts & support schedules'!D$81 -> 0.085642198 | E56: ='Forecasts & support schedules'!E76/'Forecasts & support schedules'!E$81 -> 0.22946239 | F56: ='Forecasts & support schedules'!F76/'Forecasts & support schedules'!F$81 -> 0.13864237 | G56: ='Forecasts & support schedules'!G76/'Forecasts & support schedules'!G$81 -> 0.28917816 | H56: ='Forecasts & support schedules'!H76/'Forecasts & support schedules'!H$81 -> 0.25336165
B57: ='Forecasts & support schedules'!B77 -> ( vi ) Loans | D57: ='Forecasts & support schedules'!D77/'Forecasts & support schedules'!D$81 -> 6.4099023e-05 | E57: ='Forecasts & support schedules'!E77/'Forecasts & support schedules'!E$81 -> 5.4224948e-05 | F57: ='Forecasts & support schedules'!F77/'Forecasts & support schedules'!F$81 -> 5.7242242e-05 | G57: ='Forecasts & support schedules'!G77/'Forecasts & support schedules'!G$81 -> 4.1393912e-05 | H57: ='Forecasts & support schedules'!H77/'Forecasts & support schedules'!H$81 -> 4.2171239e-05
B58: ='Forecasts & support schedules'!B78 -> ( vii ) Other Financial Assets | D58: ='Forecasts & support schedules'!D78/'Forecasts & support schedules'!D$81 -> 0.0025580571 | E58: ='Forecasts & support schedules'!E78/'Forecasts & support schedules'!E$81 -> 0.0037569096 | F58: ='Forecasts & support schedules'!F78/'Forecasts & support schedules'!F$81 -> 0.0067698935 | G58: ='Forecasts & support schedules'!G78/'Forecasts & support schedules'!G$81 -> 0.008642814 | H58: ='Forecasts & support schedules'!H78/'Forecasts & support schedules'!H$81 -> 0.0069232552
B59: ='Forecasts & support schedules'!B79 -> ( c ) Current Tax Assets ( Net ) | D59: ='Forecasts & support schedules'!D79/'Forecasts & support schedules'!D$81 -> 0.0056356536 | E59: ='Forecasts & support schedules'!E79/'Forecasts & support schedules'!E$81 -> 0.0053030533 | F59: ='Forecasts & support schedules'!F79/'Forecasts & support schedules'!F$81 -> 0.01341665 | G59: ='Forecasts & support schedules'!G79/'Forecasts & support schedules'!G$81 -> 0.013199374 | H59: ='Forecasts & support schedules'!H79/'Forecasts & support schedules'!H$81 -> 0.010144622
B60: ='Forecasts & support schedules'!B80 -> ( d ) Other Currents Assets | D60: ='Forecasts & support schedules'!D80/'Forecasts & support schedules'!D$81 -> 0.29155609 | E60: ='Forecasts & support schedules'!E80/'Forecasts & support schedules'!E$81 -> 0.28509206 | F60: ='Forecasts & support schedules'!F80/'Forecasts & support schedules'!F$81 -> 0.26112979 | G60: ='Forecasts & support schedules'!G80/'Forecasts & support schedules'!G$81 -> 0.2178817 | H60: ='Forecasts & support schedules'!H80/'Forecasts & support schedules'!H$81 -> 0.18592668
B61: ='Forecasts & support schedules'!B81 -> Total current assets | D61: =SUM(D50:D60) -> 1 | E61: =SUM(E50:E60) -> 1 | F61: =SUM(F50:F60) -> 1 | G61: =SUM(G50:G60) -> 1 | H61: =SUM(H50:H60) -> 1
B65: ='Forecasts & support schedules'!B86 -> EQUITY AND LIABILITIES
B66: ='Forecasts & support schedules'!B87 -> Equity
B67: ='Forecasts & support schedules'!B88 -> ( a ) Equity Share capital | D67: ='Forecasts & support schedules'!D88/'Forecasts & support schedules'!D$92 -> 0.022001757 | E67: ='Forecasts & support schedules'!E88/'Forecasts & support schedules'!E$92 -> 0.019806101 | F67: ='Forecasts & support schedules'!F88/'Forecasts & support schedules'!F$92 -> 0.052666618 | G67: ='Forecasts & support schedules'!G88/'Forecasts & support schedules'!G$92 -> 0.044723602 | H67: ='Forecasts & support schedules'!H88/'Forecasts & support schedules'!H$92 -> 0.036562108
B68: ='Forecasts & support schedules'!B89 -> ( b ) Other Equity | D68: ='Forecasts & support schedules'!D89/'Forecasts & support schedules'!D$92 -> 0.97664469 | E68: ='Forecasts & support schedules'!E89/'Forecasts & support schedules'!E$92 -> 0.97886569 | F68: ='Forecasts & support schedules'!F89/'Forecasts & support schedules'!F$92 -> 0.94605451 | G68: ='Forecasts & support schedules'!G89/'Forecasts & support schedules'!G$92 -> 0.95418 | H68: ='Forecasts & support schedules'!H89/'Forecasts & support schedules'!H$92 -> 0.96249055
B69: ='Forecasts & support schedules'!B90 -> Equity attributable to owners of the parent | D69: ='Forecasts & support schedules'!D90/'Forecasts & support schedules'!D$92 -> 0.99864645 | E69: ='Forecasts & support schedules'!E90/'Forecasts & support schedules'!E$92 -> 0.99867179 | F69: ='Forecasts & support schedules'!F90/'Forecasts & support schedules'!F$92 -> 0.99872112 | G69: ='Forecasts & support schedules'!G90/'Forecasts & support schedules'!G$92 -> 0.9989036 | H69: ='Forecasts & support schedules'!H90/'Forecasts & support schedules'!H$92 -> 0.99905266
B70: ='Forecasts & support schedules'!B91 -> Non - controlling interest | D70: ='Forecasts & support schedules'!D91/'Forecasts & support schedules'!D$92 -> 0.0013535514 | E70: ='Forecasts & support schedules'!E91/'Forecasts & support schedules'!E$92 -> 0.0013282102 | F70: ='Forecasts & support schedules'!F91/'Forecasts & support schedules'!F$92 -> 0.0012788756 | G70: ='Forecasts & support schedules'!G91/'Forecasts & support schedules'!G$92 -> 0.0010964007 | H70: ='Forecasts & support schedules'!H91/'Forecasts & support schedules'!H$92 -> 0.00094733962
B71: ='Forecasts & support schedules'!B92 -> Total equity | D71: =D69 -> 0.99864645 | E71: =E69 -> 0.99867179 | F71: =F69 -> 0.99872112 | G71: =G69 -> 0.9989036 | H71: =H69 -> 0.99905266
B73: ='Forecasts & support schedules'!B94 -> LIABILITIES
B74: ='Forecasts & support schedules'!B95 -> Non - current liabilities
B75: ='Forecasts & support schedules'!B96 -> ( a ) Financial Liabilities | D75: ='Forecasts & support schedules'!D96/'Forecasts & support schedules'!D$107 -> 0 | E75: ='Forecasts & support schedules'!E96/'Forecasts & support schedules'!E$107 -> 0 | F75: ='Forecasts & support schedules'!F96/'Forecasts & support schedules'!F$107 -> 0 | G75: ='Forecasts & support schedules'!G96/'Forecasts & support schedules'!G$107 -> 0 | H75: ='Forecasts & support schedules'!H96/'Forecasts & support schedules'!H$107 -> 0
B76: ='Forecasts & support schedules'!B97 -> ( i ) Borrowings | D76: ='Forecasts & support schedules'!D97/'Forecasts & support schedules'!D$107 -> 0 | E76: ='Forecasts & support schedules'!E97/'Forecasts & support schedules'!E$107 -> 0 | F76: ='Forecasts & support schedules'!F97/'Forecasts & support schedules'!F$107 -> 0 | G76: ='Forecasts & support schedules'!G97/'Forecasts & support schedules'!G$107 -> 0 | H76: ='Forecasts & support schedules'!H97/'Forecasts & support schedules'!H$107 -> 0
B77: ='Forecasts & support schedules'!B98 -> ( ia ) Lease Liabilities | D77: ='Forecasts & support schedules'!D98/'Forecasts & support schedules'!D$107 -> 0.00073791429 | E77: ='Forecasts & support schedules'!E98/'Forecasts & support schedules'!E$107 -> 0.025408554 | F77: ='Forecasts & support schedules'!F98/'Forecasts & support schedules'!F$107 -> 0.05680634 | G77: ='Forecasts & support schedules'!G98/'Forecasts & support schedules'!G$107 -> 0.052139223 | H77: ='Forecasts & support schedules'!H98/'Forecasts & support schedules'!H$107 -> 0.054017985
B78: ='Forecasts & support schedules'!B99 -> ( ii ) Trade payables | D78: ='Forecasts & support schedules'!D99/'Forecasts & support schedules'!D$107 -> 0 | E78: ='Forecasts & support schedules'!E99/'Forecasts & support schedules'!E$107 -> 0 | F78: ='Forecasts & support schedules'!F99/'Forecasts & support schedules'!F$107 -> 0 | G78: ='Forecasts & support schedules'!G99/'Forecasts & support schedules'!G$107 -> 0 | H78: ='Forecasts & support schedules'!H99/'Forecasts & support schedules'!H$107 -> 0
B79: ='Forecasts & support schedules'!B100 -> A ) total outstanding dues of micro enterprises and small enterprises | D79: ='Forecasts & support schedules'!D100/'Forecasts & support schedules'!D$107 -> 0 | E79: ='Forecasts & support schedules'!E100/'Forecasts & support schedules'!E$107 -> 0 | F79: ='Forecasts & support schedules'!F100/'Forecasts & support schedules'!F$107 -> 0 | G79: ='Forecasts & support schedules'!G100/'Forecasts & support schedules'!G$107 -> 0 | H79: ='Forecasts & support schedules'!H100/'Forecasts & support schedules'!H$107 -> 0
B80: ='Forecasts & support schedules'!B101 -> B ) total outstanding dues of creditors other than micro enterprises and small enterprises | D80: ='Forecasts & support schedules'!D101/'Forecasts & support schedules'!D$107 -> 0.00018290183 | E80: ='Forecasts & support schedules'!E101/'Forecasts & support schedules'!E$107 -> 0.00016771323 | F80: ='Forecasts & support schedules'!F101/'Forecasts & support schedules'!F$107 -> 0.00035372511 | G80: ='Forecasts & support schedules'!G101/'Forecasts & support schedules'!G$107 -> 0 | H80: ='Forecasts & support schedules'!H101/'Forecasts & support schedules'!H$107 -> 0
B81: ='Forecasts & support schedules'!B102 -> Sub Total - Trade payables | D81: ='Forecasts & support schedules'!D102/'Forecasts & support schedules'!D$107 -> 0 | E81: ='Forecasts & support schedules'!E102/'Forecasts & support schedules'!E$107 -> 0 | F81: ='Forecasts & support schedules'!F102/'Forecasts & support schedules'!F$107 -> 0 | G81: ='Forecasts & support schedules'!G102/'Forecasts & support schedules'!G$107 -> 0 | H81: ='Forecasts & support schedules'!H102/'Forecasts & support schedules'!H$107 -> 0
B82: ='Forecasts & support schedules'!B103 -> ( iii ) Other Financial Liabilities | D82: ='Forecasts & support schedules'!D103/'Forecasts & support schedules'!D$107 -> 0.00423197 | E82: ='Forecasts & support schedules'!E103/'Forecasts & support schedules'!E$107 -> 0.0099740044 | F82: ='Forecasts & support schedules'!F103/'Forecasts & support schedules'!F$107 -> 0.0045219453 | G82: ='Forecasts & support schedules'!G103/'Forecasts & support schedules'!G$107 -> 0.0041538302 | H82: ='Forecasts & support schedules'!H103/'Forecasts & support schedules'!H$107 -> 0.013410156
B83: ='Forecasts & support schedules'!B104 -> ( b ) Provisions | D83: ='Forecasts & support schedules'!D104/'Forecasts & support schedules'!D$107 -> 0.89056163 | E83: ='Forecasts & support schedules'!E104/'Forecasts & support schedules'!E$107 -> 0.89051779 | F83: ='Forecasts & support schedules'!F104/'Forecasts & support schedules'!F$107 -> 0.80749706 | G83: ='Forecasts & support schedules'!G104/'Forecasts & support schedules'!G$107 -> 0.83706601 | H83: ='Forecasts & support schedules'!H104/'Forecasts & support schedules'!H$107 -> 0.83034358
B84: ='Forecasts & support schedules'!B105 -> ( c ) Deferred Tax Liabilities ( Net ) | D84: ='Forecasts & support schedules'!D105/'Forecasts & support schedules'!D$107 -> 0.00022705055 | E84: ='Forecasts & support schedules'!E105/'Forecasts & support schedules'!E$107 -> 0.0007152476 | F84: ='Forecasts & support schedules'!F105/'Forecasts & support schedules'!F$107 -> 0.0027628799 | G84: ='Forecasts & support schedules'!G105/'Forecasts & support schedules'!G$107 -> 0.0047336356 | H84: ='Forecasts & support schedules'!H105/'Forecasts & support schedules'!H$107 -> 0.0087621607
B85: ='Forecasts & support schedules'!B106 -> ( d ) Other Non - Current Liabilities | D85: ='Forecasts & support schedules'!D106/'Forecasts & support schedules'!D$107 -> 0.10405853 | E85: ='Forecasts & support schedules'!E106/'Forecasts & support schedules'!E$107 -> 0.07321669 | F85: ='Forecasts & support schedules'!F106/'Forecasts & support schedules'!F$107 -> 0.12805805 | G85: ='Forecasts & support schedules'!G106/'Forecasts & support schedules'!G$107 -> 0.1019073 | H85: ='Forecasts & support schedules'!H106/'Forecasts & support schedules'!H$107 -> 0.093466116
B86: ='Forecasts & support schedules'!B107 -> Total non - current liabilities | D86: =SUM(D75:D85) -> 1 | E86: =SUM(E75:E85) -> 1 | F86: =SUM(F75:F85) -> 1 | G86: =SUM(G75:G85) -> 1 | H86: =SUM(H75:H85) -> 1
B88: ='Forecasts & support schedules'!B109 -> Current Liabilities
B89: ='Forecasts & support schedules'!B110 -> ( a ) Financial liabilities | D89: ='Forecasts & support schedules'!D110/'Forecasts & support schedules'!D$122 -> 0 | E89: ='Forecasts & support schedules'!E110/'Forecasts & support schedules'!E$122 -> 0 | F89: ='Forecasts & support schedules'!F110/'Forecasts & support schedules'!F$122 -> 0 | G89: ='Forecasts & support schedules'!G110/'Forecasts & support schedules'!G$122 -> 0 | H89: ='Forecasts & support schedules'!H110/'Forecasts & support schedules'!H$122 -> 0
B90: ='Forecasts & support schedules'!B111 -> ( i ) Borrowings | D90: ='Forecasts & support schedules'!D111/'Forecasts & support schedules'!D$122 -> 0 | E90: ='Forecasts & support schedules'!E111/'Forecasts & support schedules'!E$122 -> 0 | F90: ='Forecasts & support schedules'!F111/'Forecasts & support schedules'!F$122 -> 0 | G90: ='Forecasts & support schedules'!G111/'Forecasts & support schedules'!G$122 -> 0 | H90: ='Forecasts & support schedules'!H111/'Forecasts & support schedules'!H$122 -> 0
B91: ='Forecasts & support schedules'!B112 -> ( ia ) Lease Liabilities | D91: ='Forecasts & support schedules'!D112/'Forecasts & support schedules'!D$122 -> 8.0216049e-05 | E91: ='Forecasts & support schedules'!E112/'Forecasts & support schedules'!E$122 -> 6.0773074e-05 | F91: ='Forecasts & support schedules'!F112/'Forecasts & support schedules'!F$122 -> 9.3358968e-05 | G91: ='Forecasts & support schedules'!G112/'Forecasts & support schedules'!G$122 -> 0.00010260261 | H91: ='Forecasts & support schedules'!H112/'Forecasts & support schedules'!H$122 -> 0.00012859106
B92: ='Forecasts & support schedules'!B113 -> ( ii ) Trade payables | D92: ='Forecasts & support schedules'!D113/'Forecasts & support schedules'!D$122 -> 0 | E92: ='Forecasts & support schedules'!E113/'Forecasts & support schedules'!E$122 -> 0 | F92: ='Forecasts & support schedules'!F113/'Forecasts & support schedules'!F$122 -> 0 | G92: ='Forecasts & support schedules'!G113/'Forecasts & support schedules'!G$122 -> 0 | H92: ='Forecasts & support schedules'!H113/'Forecasts & support schedules'!H$122 -> 0
B93: ='Forecasts & support schedules'!B114 -> A ) total outstanding dues of micro enterprises and small enterprises | D93: ='Forecasts & support schedules'!D114/'Forecasts & support schedules'!D$122 -> 0.0091167025 | E93: ='Forecasts & support schedules'!E114/'Forecasts & support schedules'!E$122 -> 0.012687784 | F93: ='Forecasts & support schedules'!F114/'Forecasts & support schedules'!F$122 -> 0.010091521 | G93: ='Forecasts & support schedules'!G114/'Forecasts & support schedules'!G$122 -> 0.009672793 | H93: ='Forecasts & support schedules'!H114/'Forecasts & support schedules'!H$122 -> 0.0089998552
B94: ='Forecasts & support schedules'!B115 -> B ) total outstanding dues of creditors other than micro enterprises and small enterprises | D94: ='Forecasts & support schedules'!D115/'Forecasts & support schedules'!D$122 -> 0.18690161 | E94: ='Forecasts & support schedules'!E115/'Forecasts & support schedules'!E$122 -> 0.15938173 | F94: ='Forecasts & support schedules'!F115/'Forecasts & support schedules'!F$122 -> 0.15184642 | G94: ='Forecasts & support schedules'!G115/'Forecasts & support schedules'!G$122 -> 0.1585914 | H94: ='Forecasts & support schedules'!H115/'Forecasts & support schedules'!H$122 -> 0.16003005
B95: ='Forecasts & support schedules'!B116 -> Sub Total - Trade payables | D95: ='Forecasts & support schedules'!D116/'Forecasts & support schedules'!D$122 -> 0.19601831 | E95: ='Forecasts & support schedules'!E116/'Forecasts & support schedules'!E$122 -> 0.17206951 | F95: ='Forecasts & support schedules'!F116/'Forecasts & support schedules'!F$122 -> 0.16193794 | G95: ='Forecasts & support schedules'!G116/'Forecasts & support schedules'!G$122 -> 0.1682642 | H95: ='Forecasts & support schedules'!H116/'Forecasts & support schedules'!H$122 -> 0.16902991
B96: ='Forecasts & support schedules'!B117 -> ( iii ) Other Financial liabilities | D96: ='Forecasts & support schedules'!D117/'Forecasts & support schedules'!D$122 -> 0.056980133 | E96: ='Forecasts & support schedules'!E117/'Forecasts & support schedules'!E$122 -> 0.049048978 | F96: ='Forecasts & support schedules'!F117/'Forecasts & support schedules'!F$122 -> 0.06273674 | G96: ='Forecasts & support schedules'!G117/'Forecasts & support schedules'!G$122 -> 0.059797346 | H96: ='Forecasts & support schedules'!H117/'Forecasts & support schedules'!H$122 -> 0.069273116
B97: ='Forecasts & support schedules'!B118 -> ( b ) Other Current Liabilities | D97: ='Forecasts & support schedules'!D118/'Forecasts & support schedules'!D$122 -> 0.72509128 | E97: ='Forecasts & support schedules'!E118/'Forecasts & support schedules'!E$122 -> 0.7562964 | F97: ='Forecasts & support schedules'!F118/'Forecasts & support schedules'!F$122 -> 0.74390857 | G97: ='Forecasts & support schedules'!G118/'Forecasts & support schedules'!G$122 -> 0.73954872 | H97: ='Forecasts & support schedules'!H118/'Forecasts & support schedules'!H$122 -> 0.7233004
B98: ='Forecasts & support schedules'!B119 -> ( c ) Provisions | D98: ='Forecasts & support schedules'!D119/'Forecasts & support schedules'!D$122 -> 0.020813391 | E98: ='Forecasts & support schedules'!E119/'Forecasts & support schedules'!E$122 -> 0.021644407 | F98: ='Forecasts & support schedules'!F119/'Forecasts & support schedules'!F$122 -> 0.030513795 | G98: ='Forecasts & support schedules'!G119/'Forecasts & support schedules'!G$122 -> 0.031531235 | H98: ='Forecasts & support schedules'!H119/'Forecasts & support schedules'!H$122 -> 0.037448855
B99: ='Forecasts & support schedules'!B120 -> ( d ) Current tax liabilities ( Net ) | D99: ='Forecasts & support schedules'!D120/'Forecasts & support schedules'!D$122 -> 0 | E99: ='Forecasts & support schedules'!E120/'Forecasts & support schedules'!E$122 -> 3.5238169e-05 | F99: ='Forecasts & support schedules'!F120/'Forecasts & support schedules'!F$122 -> 0 | G99: ='Forecasts & support schedules'!G120/'Forecasts & support schedules'!G$122 -> 1.2711828e-05 | H99: ='Forecasts & support schedules'!H120/'Forecasts & support schedules'!H$122 -> 0
B100: ='Forecasts & support schedules'!B121 -> ( e ) Deferred Income | D100: ='Forecasts & support schedules'!D121/'Forecasts & support schedules'!D$122 -> 0.0010166641 | E100: ='Forecasts & support schedules'!E121/'Forecasts & support schedules'!E$122 -> 0.00084469466 | F100: ='Forecasts & support schedules'!F121/'Forecasts & support schedules'!F$122 -> 0.0008095973 | G100: ='Forecasts & support schedules'!G121/'Forecasts & support schedules'!G$122 -> 0.00074318794 | H100: ='Forecasts & support schedules'!H121/'Forecasts & support schedules'!H$122 -> 0.00081913516
B101: ='Forecasts & support schedules'!B122 -> Total current liabilities | D101: =SUM(D89:D91,D95:D100) -> 1 | E101: =SUM(E89:E91,E95:E100) -> 1 | F101: =SUM(F89:F91,F95:F100) -> 1 | G101: =SUM(G89:G91,G95:G100) -> 1 | H101: =SUM(H89:H91,H95:H100) -> 1

Sheet Profit & Loss
A1: ='Data Sheet'!B1 -> BHARAT ELECTRONICS LTD | H1: =UPDATE | M1: SCREENER.IN
A3: Narration | B3: ='Data Sheet'!B16 -> 42460 | C3: ='Data Sheet'!C16 -> 42825 | D3: ='Data Sheet'!D16 -> 43190 | E3: ='Data Sheet'!E16 -> 43555 | F3: ='Data Sheet'!F16 -> 43921 | G3: ='Data Sheet'!G16 -> 44286 | H3: ='Data Sheet'!H16 -> 44651 | I3: ='Data Sheet'!I16 -> 45016 | ... K3: ='Data Sheet'!K16 -> 45747 | L3: Trailing | M3: Best Case | N3: Worst Case
A4: Sales | B4: ='Data Sheet'!B17 -> 7353.77 | C4: ='Data Sheet'!C17 -> 8656.39 | D4: ='Data Sheet'!D17 -> 10400.8 | E4: ='Data Sheet'!E17 -> 12164.17 | F4: ='Data Sheet'!F17 -> 12967.67 | G4: ='Data Sheet'!G17 -> 14108.69 | H4: ='Data Sheet'!H17 -> 15368.18 | I4: ='Data Sheet'!I17 -> 17734.44 | ... K4: ='Data Sheet'!K17 -> 23768.75 | L4: =SUM(Quarters!I4:L4) -> 26535.27 | M4: =$K4+M23*K4 -> 27873.83 | N4: =$K4+N23*L4 -> 27094.222
A5: Expenses | B5: =SUM('Data Sheet'!B18,'Data Sheet'!B20:B24, -1*'Data Sheet'!B19) -> 5960.74 | C5: =SUM('Data Sheet'!C18,'Data Sheet'!C20:C24, -1*'Data Sheet'!C19) -> 6864.43 | D5: =SUM('Data Sheet'!D18,'Data Sheet'!D20:D24, -1*'Data Sheet'!D19) -> 8361.42 | E5: =SUM('Data Sheet'!E18,'Data Sheet'!E20:E24, -1*'Data Sheet'!E19) -> 9254.76 | F5: =SUM('Data Sheet'!F18,'Data Sheet'!F20:F24, -1*'Data Sheet'!F19) -> 10209.15 | G5: =SUM('Data Sheet'!G18,'Data Sheet'!G20:G24, -1*'Data Sheet'!G19) -> 10894.94 | H5: =SUM('Data Sheet'!H18,'Data Sheet'!H20:H24, -1*'Data Sheet'!H19) -> 12023.8 | I5: =SUM('Data Sheet'!I18,'Data Sheet'!I20:I24, -1*'Data Sheet'!I19) -> 13644.68 | ... K5: =SUM('Data Sheet'!K18,'Data Sheet'!K20:K24, -1*'Data Sheet'!K19) -> 16932.2 | L5: =SUM(Quarters!I5:L5) -> 18651.53 | M5: =M4-M6 -> 19592.398 | N5: =N4-N6 -> 20751.337
A6: Operating Profit | B6: =B4-B5 -> 1393.03 | C6: =C4-C5 -> 1791.96 | D6: =D4-D5 -> 2039.38 | E6: =E4-E5 -> 2909.41 | F6: =F4-F5 -> 2758.52 | G6: =G4-G5 -> 3213.75 | H6: =H4-H5 -> 3344.38 | I6: =I4-I5 -> 4089.76 | ... K6: =K4-K5 -> 6836.55 | L6: =SUM(Quarters!I6:L6) -> 7883.74 | M6: =M4*M24 -> 8281.4318 | N6: =N4*N24 -> 6342.8852
A7: Other Income | B7: ='Data Sheet'!B25 -> 572.64 | C7: ='Data Sheet'!C25 -> 420.11 | D7: ='Data Sheet'!D25 -> 195.73 | E7: ='Data Sheet'!E25 -> 72.99 | F7: ='Data Sheet'!F25 -> 99.4 | G7: ='Data Sheet'!G25 -> 124.96 | H7: ='Data Sheet'!H25 -> 231.54 | I7: ='Data Sheet'!I25 -> 280.8 | ... K7: ='Data Sheet'!K25 -> 742.36 | L7: =SUM(Quarters!I7:L7) -> 650.42 | M7: 0 | N7: 0
A8: Depreciation | B8: ='Data Sheet'!B26 -> 191.96 | C8: ='Data Sheet'!C26 -> 211.63 | D8: ='Data Sheet'!D26 -> 271.72 | E8: ='Data Sheet'!E26 -> 338.13 | F8: ='Data Sheet'!F26 -> 371.86 | G8: ='Data Sheet'!G26 -> 387.32 | H8: ='Data Sheet'!H26 -> 401.13 | I8: ='Data Sheet'!I26 -> 428.82 | ... K8: ='Data Sheet'!K26 -> 467.38 | L8: =SUM(Quarters!I8:L8) -> 520.3 | M8: =+$L8 -> 520.3 | N8: =+$L8 -> 520.3
A9: Interest | B9: ='Data Sheet'!B27 -> 9.74 | C9: ='Data Sheet'!C27 -> 17.87 | D9: ='Data Sheet'!D27 -> 6.36 | E9: ='Data Sheet'!E27 -> 15.93 | F9: ='Data Sheet'!F27 -> 7.66 | G9: ='Data Sheet'!G27 -> 9.61 | H9: ='Data Sheet'!H27 -> 8.55 | I9: ='Data Sheet'!I27 -> 18.83 | ... K9: ='Data Sheet'!K27 -> 12.53 | L9: =SUM(Quarters!I9:L9) -> 10.98 | M9: =+$L9 -> 10.98 | N9: =+$L9 -> 10.98
A10: Profit before tax | B10: ='Data Sheet'!B28 -> 1763.97 | C10: ='Data Sheet'!C28 -> 1982.57 | D10: ='Data Sheet'!D28 -> 1957.03 | E10: ='Data Sheet'!E28 -> 2628.34 | F10: ='Data Sheet'!F28 -> 2478.4 | G10: ='Data Sheet'!G28 -> 2941.78 | H10: ='Data Sheet'!H28 -> 3166.24 | I10: ='Data Sheet'!I28 -> 3922.91 | ... K10: ='Data Sheet'!K28 -> 7099 | L10: =SUM(Quarters!I10:L10) -> 8002.88 | M10: =M6+M7-SUM(M8:M9) -> 7750.1518 | N10: =N6+N7-SUM(N8:N9) -> 5811.6052
A11: Tax | B11: ='Data Sheet'!B29 -> 427.22 | C11: ='Data Sheet'!C29 -> 485.54 | D11: ='Data Sheet'!D29 -> 549.78 | E11: ='Data Sheet'!E29 -> 780.31 | F11: ='Data Sheet'!F29 -> 685.77 | G11: ='Data Sheet'!G29 -> 872.44 | H11: ='Data Sheet'!H29 -> 811.78 | I11: ='Data Sheet'!I29 -> 982.56 | ... K11: ='Data Sheet'!K29 -> 1811.85 | L11: =SUM(Quarters!I11:L11) -> 2072.59 | M11: =IF($L10>0,$L11/$L10,0) -> 0.25898052 | N11: =IF($L10>0,$L11/$L10,0) -> 0.25898052
A12: Net profit | B12: ='Data Sheet'!B30 -> 1337.39 | C12: ='Data Sheet'!C30 -> 1523.58 | D12: ='Data Sheet'!D30 -> 1431.72 | E12: ='Data Sheet'!E30 -> 1886.4 | F12: ='Data Sheet'!F30 -> 1823.85 | G12: ='Data Sheet'!G30 -> 2098.94 | H12: ='Data Sheet'!H30 -> 2398.87 | I12: ='Data Sheet'!I30 -> 2984.42 | ... K12: ='Data Sheet'!K30 -> 5321.44 | L12: =SUM(Quarters!I12:L12) -> 5963.82 | M12: =M10-M11*M10 -> 5743.0135 | N12: =N10-N11*N10 -> 4306.5127
A13: EPS | B13: =IF('Data Sheet'!B93>0,B12/'Data Sheet'!B93,0) -> 1.6886237 | C13: =IF('Data Sheet'!C93>0,C12/'Data Sheet'!C93,0) -> 2.0669923 | D13: =IF('Data Sheet'!D93>0,D12/'Data Sheet'!D93,0) -> 1.9586309 | E13: =IF('Data Sheet'!E93>0,E12/'Data Sheet'!E93,0) -> 2.5806452 | F13: =IF('Data Sheet'!F93>0,F12/'Data Sheet'!F93,0) -> 2.4950751 | G13: =IF('Data Sheet'!G93>0,G12/'Data Sheet'!G93,0) -> 2.8714055 | H13: =IF('Data Sheet'!H93>0,H12/'Data Sheet'!H93,0) -> 3.2817177 | I13: =IF('Data Sheet'!I93>0,I12/'Data Sheet'!I93,0) -> 4.0827656 | ... K13: =IF('Data Sheet'!K93>0,K12/'Data Sheet'!K93,0) -> 7.2798709 | L13: =IF('Data Sheet'!$B6>0,'Profit & Loss'!L12/'Data Sheet'!$B6,0) -> 8.1586852 | M13: =IF('Data Sheet'!$B6>0,'Profit & Loss'!M12/'Data Sheet'!$B6,0) -> 7.8566152 | N13: =IF('Data Sheet'!$B6>0,'Profit & Loss'!N12/'Data Sheet'!$B6,0) -> 5.8914389
A14: Price to earning | B14: =IF(B15>0,B15/B13,"") -> 21.970555 | C14: =IF(C15>0,C15/C13,"") -> 22.98025 | D14: =IF(D15>0,D15/D13,"") -> 24.072938 | E14: =IF(E15>0,E15/E13,"") -> 12.0435 | F14: =IF(F15>0,F15/F13,"") -> 9.9475963 | G14: =IF(G15>0,G15/G13,"") -> 14.522505 | H14: =IF(H15>0,H15/H13,"") -> 21.412567 | I14: =IF(I15>0,I15/I13,"") -> 23.893118 | ... K14: =IF(K15>0,K15/K13,"") -> 41.390844 | L14: =IF(L13>0,L15/L13,0) -> 57.53378 | M14: =M25 -> 57.53378 | N14: =N25 -> 26.066712
A15: Price | B15: ='Data Sheet'!B90 -> 37.1 | C15: ='Data Sheet'!C90 -> 47.5 | D15: ='Data Sheet'!D90 -> 47.15 | E15: ='Data Sheet'!E90 -> 31.08 | F15: ='Data Sheet'!F90 -> 24.82 | G15: ='Data Sheet'!G90 -> 41.7 | H15: ='Data Sheet'!H90 -> 70.27 | I15: ='Data Sheet'!I90 -> 97.55 | ... K15: ='Data Sheet'!K90 -> 301.32 | L15: ='Data Sheet'!B8 -> 469.4 | M15: =M13*M14 -> 452.02077 | N15: =N13*N14 -> 153.57044
A17: RATIOS:
A18: Dividend Payout | B18: =IF('Data Sheet'!B30>0, 'Data Sheet'!B31/'Data Sheet'!B30, 0) -> 0.30507182 | C18: =IF('Data Sheet'!C30>0, 'Data Sheet'!C31/'Data Sheet'!C30, 0) -> 0.32985468 | D18: =IF('Data Sheet'!D30>0, 'Data Sheet'!D31/'Data Sheet'!D30, 0) -> 0.34037382 | E18: =IF('Data Sheet'!E30>0, 'Data Sheet'!E31/'Data Sheet'!E30, 0) -> 0.43916455 | F18: =IF('Data Sheet'!F30>0, 'Data Sheet'!F31/'Data Sheet'!F30, 0) -> 0.37407133 | G18: =IF('Data Sheet'!G30>0, 'Data Sheet'!G31/'Data Sheet'!G30, 0) -> 0.46434867 | H18: =IF('Data Sheet'!H30>0, 'Data Sheet'!H31/'Data Sheet'!H30, 0) -> 0.45707771 | I18: =IF('Data Sheet'!I30>0, 'Data Sheet'!I31/'Data Sheet'!I30, 0) -> 0.44087628 | ... K18: =IF('Data Sheet'!K30>0, 'Data Sheet'!K31/'Data Sheet'!K30, 0) -> 0.3296758
A19: OPM | B19: =IF(B6>0,B6/B4,0) -> 0.18943073 | C19: =IF(C6>0,C6/C4,0) -> 0.20701008 | D19: =IF(D6>0,D6/D4,0) -> 0.19607915 | E19: =IF(E6>0,E6/E4,0) -> 0.23917867 | F19: =IF(F6>0,F6/F4,0) -> 0.21272287 | G19: =IF(G6>0,G6/G4,0) -> 0.22778515 | H19: =IF(H6>0,H6/H4,0) -> 0.21761718 | I19: =IF(I6>0,I6/I4,0) -> 0.23061117 | ... L19: =IF(L6>0,L6/L4,0) -> 0.29710419
G22: TRENDS: | H22: 10 YEARS | I22: 7 YEARS | J22: 5 YEARS | K22: 3 YEARS | L22: RECENT | M22: BEST | N22: WORST
G23: Sales Growth | H23: =IF(B4=0,"",POWER($K4/B4,1/9)-1) -> 0.13922813 | I23: =IF(D4=0,"",POWER($K4/D4,1/7)-1) -> 0.12532272 | J23: =IF(F4=0,"",POWER($K4/F4,1/5)-1) -> 0.12883087 | K23: =IF(H4=0,"",POWER($K4/H4, 1/3)-1) -> 0.15645295 | L23: =IF(ISERROR(MAX(IF(J4=0,"",(K4-J4)/J4),IF(K4=0,"",(L4-K4)/K4))),"",MAX(IF(J4=0,"",(K4-J4)/J4),IF(K4=0,"",(L4-K4)/K4))) -> 0.17270913 | M23: =MAX(K23:L23) -> 0.17270913 | N23: =MIN(H23:L23) -> 0.12532272
G24: OPM | H24: =IF(SUM(B4:$K$4)=0,"",SUMPRODUCT(B19:$K$19,B4:$K$4)/SUM(B4:$K$4)) -> 0.23410472 | I24: =IF(SUM(E4:$K$4)=0,"",SUMPRODUCT(E19:$K$19,E4:$K$4)/SUM(E4:$K$4)) -> 0.24234118 | J24: =IF(SUM(G4:$K$4)=0,"",SUMPRODUCT(G19:$K$19,G4:$K$4)/SUM(G4:$K$4)) -> 0.24697194 | K24: =IF(SUM(I4:$K$4)=0, "", SUMPRODUCT(I19:$K$19,I4:$K$4)/SUM(I4:$K$4)) -> 0.25865744 | L24: =L19 -> 0.29710419 | M24: =MAX(K24:L24) -> 0.29710419 | N24: =MIN(H24:L24) -> 0.23410472
G25: Price to Earning | H25: =IF(ISERROR(AVERAGEIF(B14:$L14,">0")),"",AVERAGEIF(B14:$L14,">0")) -> 26.066712 | I25: =IF(ISERROR(AVERAGEIF(E14:$L14,">0")),"",AVERAGEIF(E14:$L14,">0")) -> 27.213761 | J25: =IF(ISERROR(AVERAGEIF(G14:$L14,">0")),"",AVERAGEIF(G14:$L14,">0")) -> 32.619832 | K25: =IF(ISERROR(AVERAGEIF(I14:$L14,">0")),"",AVERAGEIF(I14:$L14,">0")) -> 39.94598 | L25: =L14 -> 57.53378 | M25: =MAX(K25:L25) -> 57.53378 | N25: =MIN(H25:L25) -> 26.066712

Sheet Quarters
C1: Bharat Electronics Ltd
B3: Narration | C3: ='Data Sheet'!B41 -> 45199 | D3: ='Data Sheet'!C41 -> 45291 | E3: ='Data Sheet'!D41 -> 45382 | F3: ='Data Sheet'!E41 -> 45473 | G3: ='Data Sheet'!F41 -> 45565 | H3: ='Data Sheet'!G41 -> 45657 | I3: ='Data Sheet'!H41 -> 45747 | J3: ='Data Sheet'!I41 -> 45838 | ... L3: ='Data Sheet'!K41 -> 46022
B4: Sales | C4: ='Data Sheet'!B42 -> 4009.06 | D4: ='Data Sheet'!C42 -> 4162.16 | E4: ='Data Sheet'!D42 -> 8564.08 | F4: ='Data Sheet'!E42 -> 4243.57 | G4: ='Data Sheet'!F42 -> 4604.9 | H4: ='Data Sheet'!G42 -> 5770.69 | I4: ='Data Sheet'!H42 -> 9149.59 | J4: ='Data Sheet'!I42 -> 4439.74 | ... L4: ='Data Sheet'!K42 -> 7153.85
B5: Expenses | C5: ='Data Sheet'!B43 -> 2994.89 | D5: ='Data Sheet'!C43 -> 3089.66 | E5: ='Data Sheet'!D43 -> 6276.85 | F5: ='Data Sheet'!E43 -> 3295.37 | G5: ='Data Sheet'!F43 -> 3204.95 | H5: ='Data Sheet'!G43 -> 4101.2 | I5: ='Data Sheet'!H43 -> 6333.53 | J5: ='Data Sheet'!I43 -> 3201.47 | ... L5: ='Data Sheet'!K43 -> 5026.61
B6: Operating Profit | C6: ='Data Sheet'!B50 -> 1014.17 | D6: ='Data Sheet'!C50 -> 1072.5 | E6: ='Data Sheet'!D50 -> 2287.23 | F6: ='Data Sheet'!E50 -> 948.2 | G6: ='Data Sheet'!F50 -> 1399.95 | H6: ='Data Sheet'!G50 -> 1669.49 | I6: ='Data Sheet'!H50 -> 2816.06 | J6: ='Data Sheet'!I50 -> 1238.27 | ... L6: ='Data Sheet'!K50 -> 2127.24
B7: Other Income | C7: ='Data Sheet'!B44 -> 137.06 | D7: ='Data Sheet'!C44 -> 167.42 | E7: ='Data Sheet'!D44 -> 225.43 | F7: ='Data Sheet'!E44 -> 203.58 | G7: ='Data Sheet'!F44 -> 157.76 | H7: ='Data Sheet'!G44 -> 186.38 | I7: ='Data Sheet'!H44 -> 194.64 | J7: ='Data Sheet'!I44 -> 163.32 | ... L7: ='Data Sheet'!K44 -> 138.54
B8: Depreciation | C8: ='Data Sheet'!B45 -> 108.26 | D8: ='Data Sheet'!C45 -> 107.46 | E8: ='Data Sheet'!D45 -> 118.54 | F8: ='Data Sheet'!E45 -> 107.68 | G8: ='Data Sheet'!F45 -> 111.19 | H8: ='Data Sheet'!G45 -> 110.93 | I8: ='Data Sheet'!H45 -> 137.58 | J8: ='Data Sheet'!I45 -> 120.79 | ... L8: ='Data Sheet'!K45 -> 135.44
B9: Interest | C9: ='Data Sheet'!B46 -> 1.51 | D9: ='Data Sheet'!C46 -> 0.51 | E9: ='Data Sheet'!D46 -> 4.05 | F9: ='Data Sheet'!E46 -> 1.18 | G9: ='Data Sheet'!F46 -> 1.32 | H9: ='Data Sheet'!G46 -> 1.32 | I9: ='Data Sheet'!H46 -> 5.86 | J9: ='Data Sheet'!I46 -> 1.44 | ... L9: ='Data Sheet'!K46 -> 2.03
B10: Profit before tax | C10: ='Data Sheet'!B47 -> 1041.46 | D10: ='Data Sheet'!C47 -> 1131.95 | E10: ='Data Sheet'!D47 -> 2390.07 | F10: ='Data Sheet'!E47 -> 1042.92 | G10: ='Data Sheet'!F47 -> 1445.2 | H10: ='Data Sheet'!G47 -> 1743.62 | I10: ='Data Sheet'!H47 -> 2867.26 | J10: ='Data Sheet'!I47 -> 1279.36 | ... L10: ='Data Sheet'!K47 -> 2128.31
B11: Tax | C11: ='Data Sheet'!B48 -> 260.73 | D11: ='Data Sheet'!C48 -> 283.83 | E11: ='Data Sheet'!D48 -> 604.41 | F11: ='Data Sheet'!E48 -> 261.93 | G11: ='Data Sheet'!F48 -> 361.32 | H11: ='Data Sheet'!G48 -> 442.35 | I11: ='Data Sheet'!H48 -> 746.25 | J11: ='Data Sheet'!I48 -> 318.69 | ... L11: ='Data Sheet'!K48 -> 558.12
B12: Net profit | C12: ='Data Sheet'!B49 -> 789.35 | D12: ='Data Sheet'!C49 -> 859.58 | E12: ='Data Sheet'!D49 -> 1797.11 | F12: ='Data Sheet'!E49 -> 791 | G12: ='Data Sheet'!F49 -> 1092.45 | H12: ='Data Sheet'!G49 -> 1310.95 | I12: ='Data Sheet'!H49 -> 2127.04 | J12: ='Data Sheet'!I49 -> 969.91 | ... L12: ='Data Sheet'!K49 -> 1579.1
B14: OPM | C14: =IF(C4>0,C6/C4,"") -> 0.25296952 | D14: =IF(D4>0,D6/D4,"") -> 0.25767871 | E14: =IF(E4>0,E6/E4,"") -> 0.26707247 | F14: =IF(F4>0,F6/F4,"") -> 0.22344394 | G14: =IF(G4>0,G6/G4,"") -> 0.30401312 | H14: =IF(H4>0,H6/H4,"") -> 0.28930509 | I14: =IF(I4>0,I6/I4,"") -> 0.30777991 | J14: =IF(J4>0,J6/J4,"") -> 0.27890597 | ... L14: =IF(L4>0,L6/L4,"") -> 0.29735597

Sheet DCF valuation & sensitivity
A1: Bharat Electronics Ltd
A3: DCF Model
B5: Particulars | C5: Value | G5: Sensitivity Analysis
B6: Transaction Date | C6: 45516
B7: Fiscal Year End | C7: 45747 | H7: Sensitivties - Intrinsic Value (Rs./Share)
B8: Risk Free Rate | C8: 0.0719
B9: Tax Rate | C9: 0.255 | J9: Exit Multiple
B10: EV/EBITDA Multiple | C10: 40.43x | J10: 28.0x | K10: 30.0x | L10: 40.4x | M10: 34.0x | N10: 36.0x
B11: Perpetual Growth Rate | C11: 0.06 | E11: Method | F11: Value (₹ MM) | H11: Discount Rate | I11: 0.12 | J11: 326 | K11: 344 | L11: 442 | M11: 382 | N11: 401
B12: Discount Rate (WACC) | C12: 0.1271 | E12: EV/EBITDA Method | F12: 86047422 | I12: 0.13 | J12: 301 | K12: 318 | L12: 408 | M12: 352 | N12: 370
B13: Shares Outstanding | C13: 73098 | E13: Perpetual Growth Method | F13: 19540687 | I13: 0.1271 | J13: 308 | K13: 325 | L13: 417 | M13: 361 | N13: 378
B14: Current Price | C14: 272 | E14: Average Terminal Value | F14: 52794055 | I14: 0.15 | J14: 258 | K14: 272 | L14: 347 | M14: 301 | N14: 315
I15: 0.17 | J15: 222 | K15: 234 | L15: 297 | M15: 258 | N15: 270
B16: Particulars | C16: Amount (₹ MM)
B17: PV of FCFFs | C17: 3538862
B18: PV of Terminal Value | C18: 15957341 | J18: Perpetual Growth Rate
B19: Enterprise Value | C19: 19496203 | J19: 0.04 | K19: 0.05 | L19: 0.06 | M19: 0.07 | N19: 0.08
B20: + Cash & Equivalents | C20: 954510 | H20: Discount Rate | I20: 0.12 | J20: 3135.6319 | K20: 3177.1291 | L20: 3232.4589 | M20: 3309.9204 | N20: 3426.1128
B21: - Debt | C21: -589 | I21: 0.13 | J21: 2912.453 | K21: 2942.3431 | L21: 2980.7733 | M21: 3032.0134 | N21: 3103.7497
B22: - Non-Controlling Interest | C22: -1894 | I22: 0.10377822 | J22: 3573.3901 | K22: 3650.2435 | L22: 3762.2073 | M22: 3940.4646 | N22: 4268.6552
B23: Equity Value | C23: 20448230 | I23: 0.15 | J23: 2541.5051 | K23: 2558.3182 | L23: 2578.8675 | M23: 2604.5542 | N23: 2637.58
B24: Shares Outstanding | C24: 73,098 lakhs | I24: 0.17 | J24: 2245.33 | K24: 2255.5449 | L24: 2267.617 | M24: 2282.1035 | N24: 2299.8092
B25: Equity Value per Share | C25: 279.74
B26: Current Price | C26: 272
B27: Upside | C27: +2.8% (BUY)
B29: Year | C29: FY2026 | D29: FY2027 | E29: FY2028 | F29: FY2029 | G29: FY2030 | H29: FY2031 | I29: FY2032 | J29: FY2033 | K29: FY2034 | L29: FY2035
B30: EBIT | C30: 555821 | D30: 650311 | E30: 760864 | F30: 882602 | G30: 1014992 | H30: 1162166 | I30: 1324869 | J30: 1503727 | K30: 1699211 | L30: 1911613
B31: Cash Taxes | C31: -141734 | D31: -165829 | E31: -194020 | F31: -225063 | G31: -258823 | H31: -296352 | I31: -337842 | J31: -383450 | K31: -433299 | L31: -487461
B32: NOPAT | C32: 414087 | D32: 484482 | E32: 566844 | F32: 657538 | G32: 756169 | H32: 865814 | I32: 987028 | J32: 1120276 | K32: 1265912 | L32: 1424151
B33: D&A | C33: 63006 | D33: 73717 | E33: 86249 | F33: 100049 | G33: 115056 | H33: 131739 | I33: 150182 | J33: 170457 | K33: 192617 | L33: 216694
B34: Capex | C34: -99459 | D34: -116368 | E34: -136150 | F34: -157934 | G34: -181624 | H34: -207960 | I34: -237074 | J34: -269079 | K34: -304059 | L34: -342067
B35: Change in NWC | C35: -24676 | D35: -27500 | E35: -32175 | F35: -35430 | G35: -38530 | H35: -42833 | I35: -47352 | J35: -52054 | K35: -56893 | L35: -61816
B36: FCFF | C36: 352958 | D36: 414331 | E36: 484768 | F36: 564223 | G36: 651071 | H36: 746761 | I36: 852784 | J36: 969601 | K36: 1097577 | L36: 1236962

Sheet Sheet5

Sheet Balance Sheet
A1: ='Profit & Loss'!A1 -> BHARAT ELECTRONICS LTD | E1: =UPDATE | J1: SCREENER.IN
A3: Narration | B3: ='Data Sheet'!B56 -> 42460 | C3: ='Data Sheet'!C56 -> 42825 | D3: ='Data Sheet'!D56 -> 43190 | E3: ='Data Sheet'!E56 -> 43555 | F3: ='Data Sheet'!F56 -> 43921 | G3: ='Data Sheet'!G56 -> 44286 | H3: ='Data Sheet'!H56 -> 44651 | I3: ='Data Sheet'!I56 -> 45016 | ... K3: ='Data Sheet'!K56 -> 45747
A4: Equity Share Capital | B4: ='Data Sheet'!B57 -> 240 | C4: ='Data Sheet'!C57 -> 223.36 | D4: ='Data Sheet'!D57 -> 243.66 | E4: ='Data Sheet'!E57 -> 243.66 | F4: ='Data Sheet'!F57 -> 243.66 | G4: ='Data Sheet'!G57 -> 243.66 | H4: ='Data Sheet'!H57 -> 243.66 | I4: ='Data Sheet'!I57 -> 730.98 | ... K4: ='Data Sheet'!K57 -> 730.98
A5: Reserves | B5: ='Data Sheet'!B58 -> 9006.16 | C5: ='Data Sheet'!C58 -> 7512.41 | D5: ='Data Sheet'!D58 -> 7772.02 | E5: ='Data Sheet'!E58 -> 8967.84 | F5: ='Data Sheet'!F58 -> 9827.87 | G5: ='Data Sheet'!G58 -> 10815.92 | H5: ='Data Sheet'!H58 -> 12042.27 | I5: ='Data Sheet'!I58 -> 13130.65 | ... K5: ='Data Sheet'!K58 -> 19242.91
A6: Borrowings | B6: ='Data Sheet'!B59 -> 28.39 | C6: ='Data Sheet'!C59 -> 63.58 | D6: ='Data Sheet'!D59 -> 80.36 | E6: ='Data Sheet'!E59 -> 33.63 | F6: ='Data Sheet'!F59 -> 8.33 | G6: ='Data Sheet'!G59 -> 0 | H6: ='Data Sheet'!H59 -> 52.7 | I6: ='Data Sheet'!I59 -> 61.34 | ... K6: ='Data Sheet'!K59 -> 61.23
A7: Other Liabilities | B7: ='Data Sheet'!B60 -> 9330.39 | C7: ='Data Sheet'!C60 -> 9800.29 | D7: ='Data Sheet'!D60 -> 10868.48 | E7: ='Data Sheet'!E60 -> 11575.45 | F7: ='Data Sheet'!F60 -> 14270.66 | G7: ='Data Sheet'!G60 -> 18434.29 | H7: ='Data Sheet'!H60 -> 21573.51 | I7: ='Data Sheet'!I60 -> 21567.02 | ... K7: ='Data Sheet'!K60 -> 20788.45
A8: Total | B8: ='Data Sheet'!B61 -> 18604.94 | C8: ='Data Sheet'!C61 -> 17599.64 | D8: ='Data Sheet'!D61 -> 18964.52 | E8: ='Data Sheet'!E61 -> 20820.58 | F8: ='Data Sheet'!F61 -> 24350.52 | G8: ='Data Sheet'!G61 -> 29493.87 | H8: ='Data Sheet'!H61 -> 33912.14 | I8: ='Data Sheet'!I61 -> 35489.99 | ... K8: ='Data Sheet'!K61 -> 40823.57
A10: Net Block | B10: ='Data Sheet'!B62 -> 1231.84 | C10: ='Data Sheet'!C62 -> 1501.1 | D10: ='Data Sheet'!D62 -> 1839.05 | E10: ='Data Sheet'!E62 -> 2297.6 | F10: ='Data Sheet'!F62 -> 2712.59 | G10: ='Data Sheet'!G62 -> 2652.14 | H10: ='Data Sheet'!H62 -> 2675.26 | I10: ='Data Sheet'!I62 -> 2962.86 | ... K10: ='Data Sheet'!K62 -> 3419.23
A11: Capital Work in Progress | B11: ='Data Sheet'!B63 -> 429.79 | C11: ='Data Sheet'!C63 -> 742.81 | D11: ='Data Sheet'!D63 -> 940.05 | E11: ='Data Sheet'!E63 -> 849.03 | F11: ='Data Sheet'!F63 -> 827.98 | G11: ='Data Sheet'!G63 -> 882.68 | H11: ='Data Sheet'!H63 -> 1006.04 | I11: ='Data Sheet'!I63 -> 854.94 | ... K11: ='Data Sheet'!K63 -> 1051.8
A12: Investments | B12: ='Data Sheet'!B64 -> 462.46 | C12: ='Data Sheet'!C64 -> 490.96 | D12: ='Data Sheet'!D64 -> 937.34 | E12: ='Data Sheet'!E64 -> 964.42 | F12: ='Data Sheet'!F64 -> 1110.32 | G12: ='Data Sheet'!G64 -> 1305.94 | H12: ='Data Sheet'!H64 -> 1572.02 | I12: ='Data Sheet'!I64 -> 649.99 | ... K12: ='Data Sheet'!K64 -> 742.97
A13: Other Assets | B13: ='Data Sheet'!B65 -> 16480.85 | C13: ='Data Sheet'!C65 -> 14864.77 | D13: ='Data Sheet'!D65 -> 15248.08 | E13: ='Data Sheet'!E65 -> 16709.53 | F13: ='Data Sheet'!F65 -> 19699.63 | G13: ='Data Sheet'!G65 -> 24653.11 | H13: ='Data Sheet'!H65 -> 28658.82 | I13: ='Data Sheet'!I65 -> 31022.2 | ... K13: ='Data Sheet'!K65 -> 35609.57
A14: Total | B14: ='Data Sheet'!B66 -> 18604.94 | C14: ='Data Sheet'!C66 -> 17599.64 | D14: ='Data Sheet'!D66 -> 18964.52 | E14: ='Data Sheet'!E66 -> 20820.58 | F14: ='Data Sheet'!F66 -> 24350.52 | G14: ='Data Sheet'!G66 -> 29493.87 | H14: ='Data Sheet'!H66 -> 33912.14 | I14: ='Data Sheet'!I66 -> 35489.99 | ... K14: ='Data Sheet'!K66 -> 40823.57
A16: Working Capital | B16: =B13-B7 -> 7150.46 | C16: =C13-C7 -> 5064.48 | D16: =D13-D7 -> 4379.6 | E16: =E13-E7 -> 5134.08 | F16: =F13-F7 -> 5428.97 | G16: =G13-G7 -> 6218.82 | H16: =H13-H7 -> 7085.31 | I16: =I13-I7 -> 9455.18 | ... K16: =K13-K7 -> 14821.12
A17: Debtors | B17: ='Data Sheet'!B67 -> 3721.91 | C17: ='Data Sheet'!C67 -> 4368.26 | D17: ='Data Sheet'!D67 -> 5014.3 | E17: ='Data Sheet'!E67 -> 5373.67 | F17: ='Data Sheet'!F67 -> 6724.02 | G17: ='Data Sheet'!G67 -> 6561.99 | H17: ='Data Sheet'!H67 -> 6108.09 | I17: ='Data Sheet'!I67 -> 7033.48 | ... K17: ='Data Sheet'!K67 -> 9116.37
A18: Inventory | B18: ='Data Sheet'!B68 -> 4157.65 | C18: ='Data Sheet'!C68 -> 4885.03 | D18: ='Data Sheet'!D68 -> 4583.37 | E18: ='Data Sheet'!E68 -> 4443.35 | F18: ='Data Sheet'!F68 -> 3960.51 | G18: ='Data Sheet'!G68 -> 4970.28 | H18: ='Data Sheet'!H68 -> 5594.91 | I18: ='Data Sheet'!I68 -> 6449.75 | ... K18: ='Data Sheet'!K68 -> 9120.21
A20: Debtor Days | B20: =IF('Profit & Loss'!B4>0,'Balance Sheet'!B17/('Profit & Loss'!B4/365),0) -> 184.73479 | C20: =IF('Profit & Loss'!C4>0,'Balance Sheet'!C17/('Profit & Loss'!C4/365),0) -> 184.18936 | D20: =IF('Profit & Loss'!D4>0,'Balance Sheet'!D17/('Profit & Loss'!D4/365),0) -> 175.96911 | E20: =IF('Profit & Loss'!E4>0,'Balance Sheet'!E17/('Profit & Loss'!E4/365),0) -> 161.24319 | F20: =IF('Profit & Loss'!F4>0,'Balance Sheet'!F17/('Profit & Loss'!F4/365),0) -> 189.26047 | G20: =IF('Profit & Loss'!G4>0,'Balance Sheet'!G17/('Profit & Loss'!G4/365),0) -> 169.76249 | H20: =IF('Profit & Loss'!H4>0,'Balance Sheet'!H17/('Profit & Loss'!H4/365),0) -> 145.06941 | I20: =IF('Profit & Loss'!I4>0,'Balance Sheet'!I17/('Profit & Loss'!I4/365),0) -> 144.75902 | ... K20: =IF('Profit & Loss'!K4>0,'Balance Sheet'!K17/('Profit & Loss'!K4/365),0) -> 139.99369
A21: Inventory Turnover | B21: =IF('Balance Sheet'!B18>0,'Profit & Loss'!B4/'Balance Sheet'!B18,0) -> 1.7687323 | C21: =IF('Balance Sheet'!C18>0,'Profit & Loss'!C4/'Balance Sheet'!C18,0) -> 1.7720239 | D21: =IF('Balance Sheet'!D18>0,'Profit & Loss'!D4/'Balance Sheet'!D18,0) -> 2.2692473 | E21: =IF('Balance Sheet'!E18>0,'Profit & Loss'!E4/'Balance Sheet'!E18,0) -> 2.7376124 | F21: =IF('Balance Sheet'!F18>0,'Profit & Loss'!F4/'Balance Sheet'!F18,0) -> 3.2742425 | G21: =IF('Balance Sheet'!G18>0,'Profit & Loss'!G4/'Balance Sheet'!G18,0) -> 2.8386107 | H21: =IF('Balance Sheet'!H18>0,'Profit & Loss'!H4/'Balance Sheet'!H18,0) -> 2.7468145 | I21: =IF('Balance Sheet'!I18>0,'Profit & Loss'!I4/'Balance Sheet'!I18,0) -> 2.7496322 | ... K21: =IF('Balance Sheet'!K18>0,'Profit & Loss'!K4/'Balance Sheet'!K18,0) -> 2.6061626
A23: Return on Equity | B23: =IF(SUM('Balance Sheet'!B4:B5)>0,'Profit & Loss'!B12/SUM('Balance Sheet'!B4:B5),"") -> 0.14464275 | C23: =IF(SUM('Balance Sheet'!C4:C5)>0,'Profit & Loss'!C12/SUM('Balance Sheet'!C4:C5),"") -> 0.1969526 | D23: =IF(SUM('Balance Sheet'!D4:D5)>0,'Profit & Loss'!D12/SUM('Balance Sheet'!D4:D5),"") -> 0.17861491 | E23: =IF(SUM('Balance Sheet'!E4:E5)>0,'Profit & Loss'!E12/SUM('Balance Sheet'!E4:E5),"") -> 0.20478749 | F23: =IF(SUM('Balance Sheet'!F4:F5)>0,'Profit & Loss'!F12/SUM('Balance Sheet'!F4:F5),"") -> 0.18108967 | G23: =IF(SUM('Balance Sheet'!G4:G5)>0,'Profit & Loss'!G12/SUM('Balance Sheet'!G4:G5),"") -> 0.18978478 | H23: =IF(SUM('Balance Sheet'!H4:H5)>0,'Profit & Loss'!H12/SUM('Balance Sheet'!H4:H5),"") -> 0.19525343 | I23: =IF(SUM('Balance Sheet'!I4:I5)>0,'Profit & Loss'!I12/SUM('Balance Sheet'!I4:I5),"") -> 0.2153008 | ... K23: =IF(SUM('Balance Sheet'!K4:K5)>0,'Profit & Loss'!K12/SUM('Balance Sheet'!K4:K5),"") -> 0.26641981
A24: Return on Capital Emp | C24: =IF((B4+B5+B6+C4+C5+C6)>0,('Profit & Loss'!C10+'Profit & Loss'!C9)*2/(B4+B5+B6+C4+C5+C6),"") -> 0.23432725 | D24: =IF((C4+C5+C6+D4+D5+D6)>0,('Profit & Loss'!D10+'Profit & Loss'!D9)*2/(C4+C5+C6+D4+D5+D6),"") -> 0.24703892 | E24: =IF((D4+D5+D6+E4+E5+E6)>0,('Profit & Loss'!E10+'Profit & Loss'!E9)*2/(D4+D5+D6+E4+E5+E6),"") -> 0.3049702 | F24: =IF((E4+E5+E6+F4+F5+F6)>0,('Profit & Loss'!F10+'Profit & Loss'!F9)*2/(E4+E5+E6+F4+F5+F6),"") -> 0.25728965 | G24: =IF((F4+F5+F6+G4+G5+G6)>0,('Profit & Loss'!G10+'Profit & Loss'!G9)*2/(F4+F5+F6+G4+G5+G6),"") -> 0.27923067 | H24: =IF((G4+G5+G6+H4+H5+H6)>0,('Profit & Loss'!H10+'Profit & Loss'!H9)*2/(G4+G5+G6+H4+H5+H6),"") -> 0.27137033 | I24: =IF((H4+H5+H6+I4+I5+I6)>0,('Profit & Loss'!I10+'Profit & Loss'!I9)*2/(H4+H5+H6+I4+I5+I6),"") -> 0.30019039 | J24: =IF((I4+I5+I6+J4+J5+J6)>0,('Profit & Loss'!J10+'Profit & Loss'!J9)*2/(I4+I5+I6+J4+J5+J6),"") -> 0.34826331 | K24: =IF((J4+J5+J6+K4+K5+K6)>0,('Profit & Loss'!K10+'Profit & Loss'!K9)*2/(J4+J5+J6+K4+K5+K6),"") -> 0.39048487

Sheet Cash Flow
A1: ='Balance Sheet'!A1 -> BHARAT ELECTRONICS LTD | E1: =UPDATE | J1: SCREENER.IN
A3: Narration | B3: ='Data Sheet'!B81 -> 42460 | C3: ='Data Sheet'!C81 -> 42825 | D3: ='Data Sheet'!D81 -> 43190 | E3: ='Data Sheet'!E81 -> 43555 | F3: ='Data Sheet'!F81 -> 43921 | G3: ='Data Sheet'!G81 -> 44286 | H3: ='Data Sheet'!H81 -> 44651 | I3: ='Data Sheet'!I81 -> 45016 | ... K3: ='Data Sheet'!K81 -> 45747
A4: Cash from Operating Activity | B4: ='Data Sheet'!B82 -> 2260.06 | C4: ='Data Sheet'!C82 -> -60.94 | D4: ='Data Sheet'!D82 -> -686.59 | E4: ='Data Sheet'!E82 -> 1513.88 | F4: ='Data Sheet'!F82 -> 2570.41 | G4: ='Data Sheet'!G82 -> 5093.22 | H4: ='Data Sheet'!H82 -> 4207.22 | I4: ='Data Sheet'!I82 -> 1266.86 | ... K4: ='Data Sheet'!K82 -> 586.62
A5: Cash from Investing Activity | B5: ='Data Sheet'!B83 -> -1470.34 | C5: ='Data Sheet'!C83 -> 3114.65 | D5: ='Data Sheet'!D83 -> -6.41 | E5: ='Data Sheet'!E83 -> -895.94 | F5: ='Data Sheet'!F83 -> -648.96 | G5: ='Data Sheet'!G83 -> -2595.22 | H5: ='Data Sheet'!H83 -> -4871.66 | I5: ='Data Sheet'!I83 -> 2690.84 | ... K5: ='Data Sheet'!K83 -> 616.94
A6: Cash from Financing Activity | B6: ='Data Sheet'!B84 -> -317.7 | C6: ='Data Sheet'!C84 -> -2856.8 | D6: ='Data Sheet'!D84 -> -1202.38 | E6: ='Data Sheet'!E84 -> -662.67 | F6: ='Data Sheet'!F84 -> -1060.52 | G6: ='Data Sheet'!G84 -> -1075.73 | H6: ='Data Sheet'!H84 -> -1077.6 | I6: ='Data Sheet'!I84 -> -1312.87 | ... K6: ='Data Sheet'!K84 -> -1696.43
A7: Net Cash Flow | B7: ='Data Sheet'!B85 -> 472.02 | C7: ='Data Sheet'!C85 -> 196.91 | D7: ='Data Sheet'!D85 -> -1895.38 | E7: ='Data Sheet'!E85 -> -44.73 | F7: ='Data Sheet'!F85 -> 860.93 | G7: ='Data Sheet'!G85 -> 1422.27 | H7: ='Data Sheet'!H85 -> -1742.04 | I7: ='Data Sheet'!I85 -> 2644.83 | ... K7: ='Data Sheet'!K85 -> -492.87

Sheet Customization
A1: How to use it?
A3: You can customize this workbook as you want.
B4: You can add custom formating, add conditional formating, add your own formulas… do ANYTHING.
B5: Please don't edit the "Data Sheet" only.
A7: After customization, you can upload this back on Screener.
B8: Upload on: | C8: https://www.screener.in/excel/
A10: Download your customized workbooks now onwards.
B11: Now whenever you will "Export to excel" from Screener, it will export your customized file.
A14: TESTING:
B15: This is a testing feature currently.
B16: You can report any formula errors on the worksheet at: support@screener.in

Sheet Data Sheet
A1: COMPANY NAME | B1: BHARAT ELECTRONICS LTD | E1: =IF(B2<>B3, "A NEW VERSION OF THE WORKSHEET IS AVAILABLE", "")
A2: LATEST VERSION | B2: 2.1 | E2: PLEASE DO NOT MAKE ANY CHANGES TO THIS SHEET
A3: CURRENT VERSION | B3: 2.1
A5: META
A6: Number of shares | B6: =IF(B9>0, B9/B8, 0) -> 730.97808
A7: Face Value | B7: 1
A8: Current Price | B8: 469.4
A9: Market Capitalization | B9: 343121.11
A15: PROFIT & LOSS
A16: Report Date | B16: 42460 | C16: 42825 | D16: 43190 | E16: 43555 | F16: 43921 | G16: 44286 | H16: 44651 | I16: 45016 | J16: 45382 | K16: 45747
A17: Sales | B17: 7353.77 | C17: 8656.39 | D17: 10400.8 | E17: 12164.17 | F17: 12967.67 | G17: 14108.69 | H17: 15368.18 | I17: 17734.44 | J17: 20268.24 | K17: 23768.75
A18: Raw Material Cost | B18: 4019.3 | C18: 4800.41 | D18: 5070.74 | E18: 6037.64 | F18: 6820.23 | G18: 7911.37 | H18: 9146.85 | I18: 10183.86 | J18: 11138.04 | K18: 13008.59
A19: Change in Inventory | B19: 232.71 | C19: 420.06 | D19: -410.89 | E19: 130.68 | F19: -249.31 | G19: 124.69 | H19: 280.28 | I19: 393.28 | J19: 561.72 | K19: 821.36
A20: Power and Fuel | B20: 45.85 | C20: 37.99 | D20: 37.78 | E20: 43.88 | F20: 41.6 | G20: 38.12 | H20: 43.13 | I20: 46.81 | J20: 57.21 | K20: 55.85
A21: Other Mfr. Exp | B21: 153.07 | C21: 129.58 | D21: 154.44 | E21: 144.1 | F21: 140.17 | G21: 168.78 | H21: 183.7 | I21: 184.06 | J21: 180.18 | K21: 339.14
A22: Employee Cost | B22: 1267.21 | C22: 1559.87 | D22: 1788.07 | E22: 1895.63 | F22: 2075.09 | G22: 1956.16 | H22: 2128.01 | I22: 2317.34 | J22: 2489.49 | K22: 2760.63
A23: Selling and admin | B23: 196.28 | C23: 214.95 | D23: 253.59 | E23: 290.54 | F23: 263.08 | G23: 326.69 | H23: 215.55 | I23: 278.86 | J23: 333.95 | K23: 364.85
A24: Other Expenses | B24: 511.74 | C24: 541.69 | D24: 645.91 | E24: 973.65 | F24: 619.67 | G24: 618.51 | H24: 586.84 | I24: 1027.03 | J24: 1579.76 | K24: 1224.5
A25: Other Income | B25: 572.64 | C25: 420.11 | D25: 195.73 | E25: 72.99 | F25: 99.4 | G25: 124.96 | H25: 231.54 | I25: 280.8 | J25: 670.14 | K25: 742.36
A26: Depreciation | B26: 191.96 | C26: 211.63 | D26: 271.72 | E26: 338.13 | F26: 371.86 | G26: 387.32 | H26: 401.13 | I26: 428.82 | J26: 443.2 | K26: 467.38
A27: Interest | B27: 9.74 | C27: 17.87 | D27: 6.36 | E27: 15.93 | F27: 7.66 | G27: 9.61 | H27: 8.55 | I27: 18.83 | J27: 12.06 | K27: 12.53
... A31: Dividend Amount | B31: 408 | C31: 502.56 | D31: 487.32 | E31: 828.44 | F31: 682.25 | G31: 974.64 | H31: 1096.47 | I31: 1315.76 | J31: 1608.16 | K31: 1754.35
A40: Quarters
A41: Report Date | B41: 45199 | C41: 45291 | D41: 45382 | E41: 45473 | F41: 45565 | G41: 45657 | H41: 45747 | I41: 45838 | J41: 45930 | K41: 46022
A42: Sales | B42: 4009.06 | C42: 4162.16 | D42: 8564.08 | E42: 4243.57 | F42: 4604.9 | G42: 5770.69 | H42: 9149.59 | I42: 4439.74 | J42: 5792.09 | K42: 7153.85
A43: Expenses | B43: 2994.89 | C43: 3089.66 | D43: 6276.85 | E43: 3295.37 | F43: 3204.95 | G43: 4101.2 | H43: 6333.53 | I43: 3201.47 | J43: 4089.92 | K43: 5026.61
A44: Other Income | B44: 137.06 | C44: 167.42 | D44: 225.43 | E44: 203.58 | F44: 157.76 | G44: 186.38 | H44: 194.64 | I44: 163.32 | J44: 153.92 | K44: 138.54
A45: Depreciation | B45: 108.26 | C45: 107.46 | D45: 118.54 | E45: 107.68 | F45: 111.19 | G45: 110.93 | H45: 137.58 | I45: 120.79 | J45: 126.49 | K45: 135.44
A46: Interest | B46: 1.51 | C46: 0.51 | D46: 4.05 | E46: 1.18 | F46: 1.32 | G46: 1.32 | H46: 5.86 | I46: 1.44 | J46: 1.65 | K46: 2.03
A47: Profit before tax | B47: 1041.46 | C47: 1131.95 | D47: 2390.07 | E47: 1042.92 | F47: 1445.2 | G47: 1743.62 | H47: 2867.26 | I47: 1279.36 | J47: 1727.95 | K47: 2128.31
A48: Tax | B48: 260.73 | C48: 283.83 | D48: 604.41 | E48: 261.93 | F48: 361.32 | G48: 442.35 | H48: 746.25 | I48: 318.69 | J48: 449.53 | K48: 558.12
A49: Net profit | B49: 789.35 | C49: 859.58 | D49: 1797.11 | E49: 791 | F49: 1092.45 | G49: 1310.95 | H49: 2127.04 | I49: 969.91 | J49: 1287.77 | K49: 1579.1
A50: Operating Profit | B50: 1014.17 | C50: 1072.5 | D50: 2287.23 | E50: 948.2 | F50: 1399.95 | G50: 1669.49 | H50: 2816.06 | I50: 1238.27 | J50: 1702.17 | K50: 2127.24
A51: Tax
A55: BALANCE SHEET
A56: Report Date | B56: 42460 | C56: 42825 | D56: 43190 | E56: 43555 | F56: 43921 | G56: 44286 | H56: 44651 | I56: 45016 | J56: 45382 | K56: 45747
A57: Equity Share Capital | B57: 240 | C57: 223.36 | D57: 243.66 | E57: 243.66 | F57: 243.66 | G57: 243.66 | H57: 243.66 | I57: 730.98 | J57: 730.98 | K57: 730.98
A58: Reserves | B58: 9006.16 | C58: 7512.41 | D58: 7772.02 | E58: 8967.84 | F58: 9827.87 | G58: 10815.92 | H58: 12042.27 | I58: 13130.65 | J58: 15595.49 | K58: 19242.91
A59: Borrowings | B59: 28.39 | C59: 63.58 | D59: 80.36 | E59: 33.63 | F59: 8.33 | H59: 52.7 | I59: 61.34 | J59: 62.51 | K59: 61.23
A60: Other Liabilities | B60: 9330.39 | C60: 9800.29 | D60: 10868.48 | E60: 11575.45 | F60: 14270.66 | G60: 18434.29 | H60: 21573.51 | I60: 21567.02 | J60: 23135.5 | K60: 20788.45
A61: Total | B61: 18604.94 | C61: 17599.64 | D61: 18964.52 | E61: 20820.58 | F61: 24350.52 | G61: 29493.87 | H61: 33912.14 | I61: 35489.99 | J61: 39524.48 | K61: 40823.57
A62: Net Block | B62: 1231.84 | C62: 1501.1 | D62: 1839.05 | E62: 2297.6 | F62: 2712.59 | G62: 2652.14 | H62: 2675.26 | I62: 2962.86 | J62: 3035.21 | K62: 3419.23
A63: Capital Work in Progress | B63: 429.79 | C63: 742.81 | D63: 940.05 | E63: 849.03 | F63: 827.98 | G63: 882.68 | H63: 1006.04 | I63: 854.94 | J63: 893.72 | K63: 1051.8
A64: Investments | B64: 462.46 | C64: 490.96 | D64: 937.34 | E64: 964.42 | F64: 1110.32 | G64: 1305.94 | H64: 1572.02 | I64: 649.99 | J64: 682.23 | K64: 742.97
A65: Other Assets | B65: 16480.85 | C65: 14864.77 | D65: 15248.08 | E65: 16709.53 | F65: 19699.63 | G65: 24653.11 | H65: 28658.82 | I65: 31022.2 | J65: 34913.32 | K65: 35609.57
A66: Total | B66: 18604.94 | C66: 17599.64 | D66: 18964.52 | E66: 20820.58 | F66: 24350.52 | G66: 29493.87 | H66: 33912.14 | I66: 35489.99 | J66: 39524.48 | K66: 40823.57
A67: Receivables | B67: 3721.91 | C67: 4368.26 | D67: 5014.3 | E67: 5373.67 | F67: 6724.02 | G67: 6561.99 | H67: 6108.09 | I67: 7033.48 | J67: 7392.38 | K67: 9116.37
A68: Inventory | B68: 4157.65 | C68: 4885.03 | D68: 4583.37 | E68: 4443.35 | F68: 3960.51 | G68: 4970.28 | H68: 5594.91 | I68: 6449.75 | J68: 7450.16 | K68: 9120.21
A69: Cash & Bank | B69: 7216.11 | C69: 3827.19 | D69: 841.07 | E69: 971.87 | F69: 1660.5 | G69: 5073.76 | H69: 7563.74 | I69: 8111.58 | J69: 11056.59 | K69: 9545.1
A70: No. of Equity Shares | B70: 240000000 | C70: 2233627930 | D70: 2436592943 | E70: 2436592943 | F70: 2436592943 | G70: 2436592943 | H70: 2436592943 | I70: 7309778829 | J70: 7309778829 | K70: 7309778829
A71: New Bonus Shares | B71: 160000000 | D71: 223362793
A72: Face value | B72: 10 | C72: 1 | D72: 1 | E72: 1 | F72: 1 | G72: 1 | H72: 1 | I72: 1 | J72: 1 | K72: 1
A80: CASH FLOW:
A81: Report Date | B81: 42460 | C81: 42825 | D81: 43190 | E81: 43555 | F81: 43921 | G81: 44286 | H81: 44651 | I81: 45016 | J81: 45382 | K81: 45747
A82: Cash from Operating Activity | B82: 2260.06 | C82: -60.94 | D82: -686.59 | E82: 1513.88 | F82: 2570.41 | G82: 5093.22 | H82: 4207.22 | I82: 1266.86 | J82: 4659.49 | K82: 586.62
A83: Cash from Investing Activity | B83: -1470.34 | C83: 3114.65 | D83: -6.41 | E83: -895.94 | F83: -648.96 | G83: -2595.22 | H83: -4871.66 | I83: 2690.84 | J83: -5923.85 | K83: 616.94
A84: Cash from Financing Activity | B84: -317.7 | C84: -2856.8 | D84: -1202.38 | E84: -662.67 | F84: -1060.52 | G84: -1075.73 | H84: -1077.6 | I84: -1312.87 | J84: -1475.01 | K84: -1696.43
A85: Net Cash Flow | B85: 472.02 | C85: 196.91 | D85: -1895.38 | E85: -44.73 | F85: 860.93 | G85: 1422.27 | H85: -1742.04 | I85: 2644.83 | J85: -2739.37 | K85: -492.87
A90: PRICE: | B90: 37.1 | C90: 47.5 | D90: 47.15 | E90: 31.08 | F90: 24.82 | G90: 41.7 | H90: 70.27 | I90: 97.55 | J90: 201.5 | K90: 301.32
A92: DERIVED:
A93: Adjusted Equity Shares in Cr | B93: 792 | C93: 737.1 | D93: 730.98 | E93: 730.98 | F93: 730.98 | G93: 730.98 | H93: 730.98 | I93: 730.98 | J93: 730.98 | K93: 730.98
